processor/processor.v
module processor(clock1, clock2);
  // 2-phase clocks:
  // - for controlled operations in each pipeline stage
  // With a single clock activating all stages at once, the successive
  // pipeline stages can work incorrectly if the input for one stage doesn't
  // arrive in time from the previous stage.
  // With 2-phase clocks each adjacent stages will be activated alternately
  // avoid this scenerio
  input clock1, clock2;

  reg [31:0] register_bank [0:15];
  reg [31:0] instruction_memory [0:1023];
  reg [31:0] data_memory [0:1023];

  // opcodes
  parameter 
    HLT = 4'b0000,
    MOV = 4'b0001,
    MVI = 4'b0010,
    LOD = 4'b0011,
    STR = 4'b0100,
    ADD = 4'b0101,
    SUB = 4'b0110,
    MUL = 4'b0111,
    AND = 4'b1000,
    ORR = 4'b1001,
    NOT = 4'b1010,
    LES = 4'b1011,
    GTR = 4'b1100,
    JEZ = 4'b1101,
    JNZ = 4'b1110,
    JMP = 4'b1111;

    

  // ----- instruction fetch (if) stage -----
  
  // states
  reg [31:0] if_pc, if_next_pc, if_ir;
  reg if_halted, if_branch_taken, if_next_branch_taken;

  initial
  begin
    if_halted <= 0;
    if_next_pc <= 0;
    if_next_branch_taken <= 0;
    id_invalid <= 1;
    ex_invalid <= 1;
    ma_invalid <= 1;
  end
  
  always @ (posedge clock1) 
  begin
    // if and ex stages are activated by the same clock 
    // so waiting some time to let the branch and halted signals from ex
    // stage come in
    #2;
    if (if_halted == 0)
    begin
      if_pc = if_next_pc;
      if_branch_taken = if_next_branch_taken;
      if (if_branch_taken == 1)
      begin
        if_ir = instruction_memory[if_pc];
        if_next_branch_taken = 0;
        if_next_pc = if_pc + 1;
      end
      else 
      begin
        if_ir = instruction_memory[if_pc];
        if_next_pc = if_pc + 1;
      end
    end
  end



  // ----- instruction decode (id) stage -----

  // states
  reg [3:0] id_opcode, id_rdest, id_ra, id_rb;
  reg [31:0] id_pc, id_rdest_val, id_ra_val, id_rb_val, id_immediate;
  reg id_invalid; // due to branch jump or program being halted, the instruction in this stage of pipeline can be invalid

  always @ (posedge clock2)
  begin 
    // instruction decoding
    id_opcode <= if_ir[31:28];
    id_rdest <= if_ir[27:24];
    id_ra <= if_ir[23:20];
    id_rb <= if_ir[19:16];
    id_rdest_val <= register_bank[if_ir[27:24]]; // register prefetching
    id_ra_val <= register_bank[if_ir[23:20]];
    id_rb_val <= register_bank[if_ir[19:16]];
    // 16-bit signed immediate number need to be converted to 32-bits
    // for that the signed bit needs to be copied as 16-MSBs
    id_immediate <= {{16{if_ir[15]}}, {if_ir[15:0]}};

    id_pc <= if_pc;
    id_invalid <= (if_branch_taken | if_halted) ? 1: 0;
  end




  // ----- execute (ex) stage: ALU and branch instruction execution -----

  // states
  reg [3:0] ex_opcode, ex_rdest, ex_ra, ex_rb;
  reg [31:0] ex_alu_result, ex_pc, ex_rdest_val, ex_ra_val, ex_rb_val, ex_immediate;
  reg ex_invalid, ex_has_result;


  always @ (posedge clock1) 
  begin
    if (id_invalid == 0) 
    begin
      ex_invalid <= 0;
      ex_opcode <= id_opcode;
      ex_pc <= id_pc;
      ex_rdest <= id_rdest;
      ex_ra <= id_ra;
      ex_rb <= id_rb;
      ex_rdest_val <= id_rdest_val;
      ex_ra_val <= id_ra_val;
      ex_rb_val <= id_rb_val;
      ex_immediate <= id_immediate;
      case (id_opcode)
        ADD: begin ex_has_result <= 1; ex_alu_result <= id_ra_val + id_rb_val; end
        SUB: begin ex_has_result <= 1; ex_alu_result <= id_ra_val - id_rb_val; end
        MUL: begin ex_has_result <= 1; ex_alu_result <= id_ra_val * id_rb_val; end
        AND: begin ex_has_result <= 1; ex_alu_result <= id_ra_val & id_rb_val; end
        ORR: begin ex_has_result <= 1; ex_alu_result <= id_ra_val | id_rb_val; end
        NOT: begin ex_has_result <= 1; ex_alu_result <= ~id_ra_val; end
        LES: begin ex_has_result <= 1; ex_alu_result <= (id_ra_val < id_rb_val) ? 1 : 0; end
        GTR: begin ex_has_result <= 1; ex_alu_result <= (id_ra_val > id_rb_val) ? 1 : 0; end
        JEZ: begin
          ex_has_result <= 0;
          if (id_rdest_val == 0) begin
            if_next_branch_taken <= 1;
            if_next_pc <= id_pc + id_immediate; // pc = pc + offset
          end
        end
        JNZ: begin
          ex_has_result <= 0;
          if (id_rdest_val != 0) begin
            if_next_branch_taken <= 1;
            if_next_pc <= id_pc + id_immediate; // pc = pc + offset
          end
        end
        JMP: begin
          ex_has_result <= 0;
          begin
            if_next_branch_taken <= 1;
            if_next_pc <= id_pc + id_immediate; // pc = pc + offset
          end
        end
        HLT: begin ex_has_result <= 0; if_halted <= 1; end
      endcase
    end
    else ex_invalid <= 1;
  end



  // ----- memory access (ma) stage: memory store and load instruction execution -----

  // states
  reg [3:0] ma_opcode, ma_rdest, ma_ra, ma_rb;
  reg [31:0] ma_alu_result, ma_ra_val, ma_immediate;
  reg ma_invalid, ma_has_result;
  
  always @ (posedge clock2)
  begin
    if (ex_invalid == 0)
    begin
      ma_invalid <= 0;
      ma_opcode <= ex_opcode;
      ma_rdest <= ex_rdest;
      ma_ra <= ex_ra;
      ma_rb <= ex_rb;
      ma_ra_val <= ex_ra_val;
      ma_immediate <= ex_immediate;
      ma_alu_result <= ex_alu_result;
      ma_has_result <= ex_has_result;
      case (ex_opcode)
        LOD: register_bank[ex_rdest] <= data_memory[ex_ra_val + ex_immediate];
        STR: data_memory[ex_ra_val + ex_immediate] <= register_bank[ex_rdest];
      endcase
    end
    else ma_invalid <= 1;
  end



  // ----- write-back (wb) stage: register move instr. + ALU result writeback

  always @ (posedge clock1)
  begin
    if (ma_invalid == 0)
    begin
      if (ma_has_result == 1) begin 
        register_bank[ma_rdest] <= ma_alu_result;
      end
      case (ma_opcode)
        MOV: register_bank[ma_rdest] <= ma_ra_val;
        MVI: register_bank[ma_rdest] <= ma_immediate;
      endcase
    end
  end


endmodule

processor/tests/simple_addition/test_simple_addition.v
/*
Assembled result of simple_addition.s

---------------------------  debug info  ---------------------------
   #0             MVI R1, 10          0010 0001 0000 0000 0000000000001010
   #1             MVI R2, 20          0010 0010 0000 0000 0000000000010100
   #2             ORR R1, R1, R1      1001 0001 0001 0001 0000000000000000
   #3             ORR R1, R1, R1      1001 0001 0001 0001 0000000000000000
   #4             ORR R1, R1, R1      1001 0001 0001 0001 0000000000000000
   #5             ORR R1, R1, R1      1001 0001 0001 0001 0000000000000000
   #6             ORR R1, R1, R1      1001 0001 0001 0001 0000000000000000
   #7             ADD R1, R1, R2      0101 0001 0001 0010 0000000000000000
   #8             HLT                 0000 0000 0000 0000 0000000000000000

----- assembled instructions -------
553648138
570425364
2433810432
2433810432
2433810432
2433810432
2433810432
1360134144
0

----- generated code -------
computer.if_next_pc = 0;
computer.instruction_memory[0]=553648138;
computer.instruction_memory[1]=570425364;
computer.instruction_memory[2]=2433810432;
computer.instruction_memory[3]=2433810432;
computer.instruction_memory[4]=2433810432;
computer.instruction_memory[5]=2433810432;
computer.instruction_memory[6]=2433810432;
computer.instruction_memory[7]=1360134144;
computer.instruction_memory[8]=0;
*/

module test_simple_addition;
reg clock1, clock2;

processor computer(clock1, clock2);

// generate 2-phase clock
initial
begin
  clock1 = 0; clock2 = 0;
  forever begin
      #5 clock1 = 1;
      #5 clock1 = 0;
      #5 clock2 = 1;
      #5 clock2 = 0;
  end
end

initial 
begin
  computer.instruction_memory[0]=553648138;
  computer.instruction_memory[1]=570425364;
  computer.instruction_memory[2]=2433810432;
  computer.instruction_memory[3]=2433810432;
  computer.instruction_memory[4]=2433810432;
  computer.instruction_memory[5]=2433810432;
  computer.instruction_memory[6]=2433810432;
  computer.instruction_memory[7]=1360134144;
  computer.instruction_memory[8]=0;
end

initial
begin
  $dumpfile("test_simple_addition.vcd");
  $dumpvars(0, test_simple_addition);
end

initial
begin
  $monitor("time: %3t  R1: %d", $time, computer.register_bank[1]);
  #1000 $finish;
end

endmodule

processor/tests/simple_addition/test_simple_addition.vcd
$date
	Sun May 26 20:23:32 2024
$end
$version
	Icarus Verilog
$end
$timescale
	1s
$end
$scope module test_simple_addition $end
$var reg 1 ! clock1 $end
$var reg 1 " clock2 $end
$scope module computer $end
$var wire 1 ! clock1 $end
$var wire 1 " clock2 $end
$var parameter 4 # ADD $end
$var parameter 4 $ AND $end
$var parameter 4 % GTR $end
$var parameter 4 & HLT $end
$var parameter 4 ' JEZ $end
$var parameter 4 ( JMP $end
$var parameter 4 ) JNZ $end
$var parameter 4 * LES $end
$var parameter 4 + LOD $end
$var parameter 4 , MOV $end
$var parameter 4 - MUL $end
$var parameter 4 . MVI $end
$var parameter 4 / NOT $end
$var parameter 4 0 ORR $end
$var parameter 4 1 STR $end
$var parameter 4 2 SUB $end
$var reg 32 3 ex_alu_result [31:0] $end
$var reg 1 4 ex_has_result $end
$var reg 32 5 ex_immediate [31:0] $end
$var reg 1 6 ex_invalid $end
$var reg 4 7 ex_opcode [3:0] $end
$var reg 32 8 ex_pc [31:0] $end
$var reg 4 9 ex_ra [3:0] $end
$var reg 32 : ex_ra_val [31:0] $end
$var reg 4 ; ex_rb [3:0] $end
$var reg 32 < ex_rb_val [31:0] $end
$var reg 4 = ex_rdest [3:0] $end
$var reg 32 > ex_rdest_val [31:0] $end
$var reg 32 ? id_immediate [31:0] $end
$var reg 1 @ id_invalid $end
$var reg 4 A id_opcode [3:0] $end
$var reg 32 B id_pc [31:0] $end
$var reg 4 C id_ra [3:0] $end
$var reg 32 D id_ra_val [31:0] $end
$var reg 4 E id_rb [3:0] $end
$var reg 32 F id_rb_val [31:0] $end
$var reg 4 G id_rdest [3:0] $end
$var reg 32 H id_rdest_val [31:0] $end
$var reg 1 I if_branch_taken $end
$var reg 1 J if_halted $end
$var reg 32 K if_ir [31:0] $end
$var reg 1 L if_next_branch_taken $end
$var reg 32 M if_next_pc [31:0] $end
$var reg 32 N if_pc [31:0] $end
$var reg 32 O ma_alu_result [31:0] $end
$var reg 1 P ma_has_result $end
$var reg 32 Q ma_immediate [31:0] $end
$var reg 1 R ma_invalid $end
$var reg 4 S ma_opcode [3:0] $end
$var reg 4 T ma_ra [3:0] $end
$var reg 32 U ma_ra_val [31:0] $end
$var reg 4 V ma_rb [3:0] $end
$var reg 4 W ma_rdest [3:0] $end
$upscope $end
$upscope $end
$enddefinitions $end
$comment Show the parameter values. $end
$dumpall
b110 2
b100 1
b1001 0
b1010 /
b10 .
b111 -
b1 ,
b11 +
b1011 *
b1110 )
b1111 (
b1101 '
b0 &
b1100 %
b1000 $
b101 #
$end
#0
$dumpvars
bx W
bx V
bx U
bx T
bx S
1R
bx Q
xP
bx O
bx N
b0 M
0L
bx K
0J
xI
bx H
bx G
bx F
bx E
bx D
bx C
bx B
bx A
1@
bx ?
bx >
bx =
bx <
bx ;
bx :
bx 9
bx 8
bx 7
16
bx 5
x4
bx 3
0"
0!
$end
#5
1!
#7
b1 M
b100001000000000000000000001010 K
0I
b0 N
#10
0!
#15
0@
b0 B
b1010 ?
b0 E
b0 C
b1 G
b10 A
1"
#20
0"
#25
b1010 5
b0 ;
b0 9
b1 =
b0 8
b10 7
06
1!
#27
b10 M
b100010000000000000000000010100 K
b1 N
#30
0!
#35
b1010 Q
b0 V
b0 T
b1 W
b10 S
0R
b1 B
b10100 ?
b10 G
1"
#40
0"
#45
b10100 5
b10 =
b1 8
1!
#47
b11 M
b10010001000100010000000000000000 K
b10 N
#50
0!
#55
b10 B
b0 ?
b1010 F
b1010 D
b1010 H
b1 E
b1 C
b1 G
b1001 A
b10100 Q
b10 W
1"
#60
0"
#65
b1010 3
14
b0 5
b1010 <
b1010 :
b1010 >
b1 ;
b1 9
b1 =
b10 8
b1001 7
1!
#67
b100 M
b11 N
#70
0!
#75
1P
b1010 O
b0 Q
b1010 U
b1 V
b1 T
b1 W
b1001 S
b11 B
1"
#80
0"
#85
b11 8
1!
#87
b101 M
b100 N
#90
0!
#95
b100 B
1"
#100
0"
#105
b100 8
1!
#107
b110 M
b101 N
#110
0!
#115
b101 B
1"
#120
0"
#125
b101 8
1!
#127
b111 M
b110 N
#130
0!
#135
b110 B
1"
#140
0"
#145
b110 8
1!
#147
b1000 M
b1010001000100100000000000000000 K
b111 N
#150
0!
#155
b111 B
b10100 F
b10 E
b101 A
1"
#160
0"
#165
b11110 3
b10100 <
b10 ;
b111 8
b101 7
1!
#167
b1001 M
b0 K
b1000 N
#170
0!
#175
b1000 B
bx F
bx D
bx H
b0 E
b0 C
b0 G
b0 A
b11110 O
b10 V
b101 S
1"
#180
0"
#185
1J
04
bx <
bx :
bx >
b0 ;
b0 9
b0 =
b1000 8
b0 7
1!
#190
0!
#195
0P
bx U
b0 V
b0 T
b0 W
b0 S
1@
1"
#200
0"
#205
16
1!
#210
0!
#215
1R
1"
