processor/processor.v
module processor(clock1, clock2);
  // 2-phase clocks:
  // - for controlled operations in each pipeline stage
  // With a single clock activating all stages at once, the successive
  // pipeline stages can work incorrectly if the input for one stage doesn't
  // arrive in time from the previous stage.
  // With 2-phase clocks each adjacent stages will be activated alternately
  // avoid this scenerio
  input clock1, clock2;

  reg [31:0] register_bank [0:15];
  reg [31:0] instruction_memory [0:1023];
  reg [31:0] data_memory [0:1023];

  // opcodes
  parameter 
    HLT = 4'b0000,
    MOV = 4'b0001,
    MVI = 4'b0010,
    LOD = 4'b0011,
    STR = 4'b0100,
    ADD = 4'b0101,
    SUB = 4'b0110,
    MUL = 4'b0111,
    AND = 4'b1000,
    ORR = 4'b1001,
    NOT = 4'b1010,
    LES = 4'b1011,
    GTR = 4'b1100,
    JEZ = 4'b1101,
    JNZ = 4'b1110,
    JMP = 4'b1111;

    

  // ----- instruction fetch (if) stage -----
  
  // states
  reg [31:0] if_pc, if_next_pc, if_ir;
  reg if_halted, if_branch_taken, if_next_branch_taken;

  initial
  begin
    if_halted <= 0;
    if_next_pc <= 0;
    if_next_branch_taken <= 0;
    id_invalid <= 1;
    ex_invalid <= 1;
    ma_invalid <= 1;
  end
  
  always @ (posedge clock1) 
  begin
    // if and ex stages are activated by the same clock 
    // so waiting some time to let the branch and halted signals from ex
    // stage come in
    #2;
    if (if_halted == 0)
    begin
      if_pc = if_next_pc;
      if_branch_taken = if_next_branch_taken;
      if (if_branch_taken == 1)
      begin
        if_ir = instruction_memory[if_pc];
        if_next_branch_taken = 0;
        if_next_pc = if_pc + 1;
      end
      else 
      begin
        if_ir = instruction_memory[if_pc];
        if_next_pc = if_pc + 1;
      end
    end
  end



  // ----- instruction decode (id) stage -----

  // states
  reg [3:0] id_opcode, id_rdest, id_ra, id_rb;
  reg [31:0] id_pc, id_rdest_val, id_ra_val, id_rb_val, id_immediate;
  reg id_invalid; // due to branch jump or program being halted, the instruction in this stage of pipeline can be invalid

  always @ (posedge clock2)
  begin 
    // instruction decoding
    id_opcode <= if_ir[31:28];
    id_rdest <= if_ir[27:24];
    id_ra <= if_ir[23:20];
    id_rb <= if_ir[19:16];
    id_rdest_val <= register_bank[if_ir[27:24]]; // register prefetching
    id_ra_val <= register_bank[if_ir[23:20]];
    id_rb_val <= register_bank[if_ir[19:16]];
    // 16-bit signed immediate number need to be converted to 32-bits
    // for that the signed bit needs to be copied as 16-MSBs
    id_immediate <= {{16{if_ir[15]}}, {if_ir[15:0]}};

    id_pc <= if_pc;
    id_invalid <= (if_branch_taken | if_halted) ? 1: 0;
  end




  // ----- execute (ex) stage: ALU and branch instruction execution -----

  // states
  reg [3:0] ex_opcode, ex_rdest, ex_ra, ex_rb;
  reg [31:0] ex_alu_result, ex_pc, ex_rdest_val, ex_ra_val, ex_rb_val, ex_immediate;
  reg ex_invalid, ex_has_result;


  always @ (posedge clock1) 
  begin
    if (id_invalid == 0) 
    begin
      ex_invalid <= 0;
      ex_opcode <= id_opcode;
      ex_pc <= id_pc;
      ex_rdest <= id_rdest;
      ex_ra <= id_ra;
      ex_rb <= id_rb;
      ex_rdest_val <= id_rdest_val;
      ex_ra_val <= id_ra_val;
      ex_rb_val <= id_rb_val;
      ex_immediate <= id_immediate;
      case (id_opcode)
        ADD: begin ex_has_result <= 1; ex_alu_result <= id_ra_val + id_rb_val; end
        SUB: begin ex_has_result <= 1; ex_alu_result <= id_ra_val - id_rb_val; end
        MUL: begin ex_has_result <= 1; ex_alu_result <= id_ra_val * id_rb_val; end
        AND: begin ex_has_result <= 1; ex_alu_result <= id_ra_val & id_rb_val; end
        ORR: begin ex_has_result <= 1; ex_alu_result <= id_ra_val | id_rb_val; end
        NOT: begin ex_has_result <= 1; ex_alu_result <= ~id_ra_val; end
        LES: begin ex_has_result <= 1; ex_alu_result <= (id_ra_val < id_rb_val) ? 1 : 0; end
        GTR: begin ex_has_result <= 1; ex_alu_result <= (id_ra_val > id_rb_val) ? 1 : 0; end
        JEZ: begin
          ex_has_result <= 0;
          if (id_rdest_val == 0) begin
            if_next_branch_taken <= 1;
            if_next_pc <= id_pc + id_immediate; // pc = pc + offset
          end
        end
        JNZ: begin
          ex_has_result <= 0;
          if (id_rdest_val != 0) begin
            if_next_branch_taken <= 1;
            if_next_pc <= id_pc + id_immediate; // pc = pc + offset
          end
        end
        JMP: begin
          ex_has_result <= 0;
          begin
            if_next_branch_taken <= 1;
            if_next_pc <= id_pc + id_immediate; // pc = pc + offset
          end
        end
        HLT: begin ex_has_result <= 0; if_halted <= 1; end
      endcase
    end
    else ex_invalid <= 1;
  end



  // ----- memory access (ma) stage: memory store and load instruction execution -----

  // states
  reg [3:0] ma_opcode, ma_rdest, ma_ra, ma_rb;
  reg [31:0] ma_alu_result, ma_ra_val, ma_immediate;
  reg ma_invalid, ma_has_result;
  
  always @ (posedge clock2)
  begin
    if (ex_invalid == 0)
    begin
      ma_invalid <= 0;
      ma_opcode <= ex_opcode;
      ma_rdest <= ex_rdest;
      ma_ra <= ex_ra;
      ma_rb <= ex_rb;
      ma_ra_val <= ex_ra_val;
      ma_immediate <= ex_immediate;
      ma_alu_result <= ex_alu_result;
      ma_has_result <= ex_has_result;
      case (ex_opcode)
        LOD: register_bank[ex_rdest] <= data_memory[ex_ra_val + ex_immediate];
        STR: data_memory[ex_ra_val + ex_immediate] <= register_bank[ex_rdest];
      endcase
    end
    else ma_invalid <= 1;
  end



  // ----- write-back (wb) stage: register move instr. + ALU result writeback

  always @ (posedge clock1)
  begin
    if (ma_invalid == 0)
    begin
      if (ma_has_result == 1) begin 
        register_bank[ma_rdest] <= ma_alu_result;
      end
      case (ma_opcode)
        MOV: register_bank[ma_rdest] <= ma_ra_val;
        MVI: register_bank[ma_rdest] <= ma_immediate;
      endcase
    end
  end


endmodule

processor/tests/memory/test_memory.v
/*

Assembling memory.s ---

---------------------------  debug info  ---------------------------
   #0             MVI R2, 8           0010 0010 0000 0000 0000000000001000
   #1             MVI R3, 1           0010 0011 0000 0000 0000000000000001
   #2      :loop  ORR R1, R1, R1      1001 0001 0001 0001 0000000000000000
   #3             ORR R1, R1, R1      1001 0001 0001 0001 0000000000000000
   #4             ORR R1, R1, R1      1001 0001 0001 0001 0000000000000000
   #5             ORR R1, R1, R1      1001 0001 0001 0001 0000000000000000
   #6             JEZ R2, continue    1101 0010 0000 0000 0000000000000100
   #7             STR R2, R2, 0       0100 0010 0010 0000 0000000000000000
   #8             SUB R2, R2, R3      0110 0010 0010 0011 0000000000000000
   #9             JMP loop            1111 0000 0000 0000 1111111111111001
  #10  :continue  ORR R1, R1, R1      1001 0001 0001 0001 0000000000000000
  #11             ORR R1, R1, R1      1001 0001 0001 0001 0000000000000000
  #12             ORR R1, R1, R1      1001 0001 0001 0001 0000000000000000
  #13             ORR R1, R1, R1      1001 0001 0001 0001 0000000000000000
  #14             MVI R1, 3           0010 0001 0000 0000 0000000000000011
  #15             ORR R1, R1, R1      1001 0001 0001 0001 0000000000000000
  #16             ORR R1, R1, R1      1001 0001 0001 0001 0000000000000000
  #17             ORR R1, R1, R1      1001 0001 0001 0001 0000000000000000
  #18             ORR R1, R1, R1      1001 0001 0001 0001 0000000000000000
  #19             ORR R1, R1, R1      1001 0001 0001 0001 0000000000000000
  #20             LOD R1, R1, 2       0011 0001 0001 0000 0000000000000010
  #21             HLT                 0000 0000 0000 0000 0000000000000000

----- assembled instructions -------
570425352
587202561
2433810432
2433810432
2433810432
2433810432
3523215364
1109393408
1646460928
4026597369
2433810432
2433810432
2433810432
2433810432
553648131
2433810432
2433810432
2433810432
2433810432
2433810432
823132162
0

----- generated code -------
computer.instruction_memory[0]=570425352;
computer.instruction_memory[1]=587202561;
computer.instruction_memory[2]=2433810432;
computer.instruction_memory[3]=2433810432;
computer.instruction_memory[4]=2433810432;
computer.instruction_memory[5]=2433810432;
computer.instruction_memory[6]=3523215364;
computer.instruction_memory[7]=1109393408;
computer.instruction_memory[8]=1646460928;
computer.instruction_memory[9]=4026597369;
computer.instruction_memory[10]=2433810432;
computer.instruction_memory[11]=2433810432;
computer.instruction_memory[12]=2433810432;
computer.instruction_memory[13]=2433810432;
computer.instruction_memory[14]=553648131;
computer.instruction_memory[15]=2433810432;
computer.instruction_memory[16]=2433810432;
computer.instruction_memory[17]=2433810432;
computer.instruction_memory[18]=2433810432;
computer.instruction_memory[19]=2433810432;
computer.instruction_memory[20]=823132162;
computer.instruction_memory[21]=0;
*/

module test_memory;
reg clock1, clock2;

processor computer(clock1, clock2);

// generate 2-phase clock
initial
begin
  clock1 = 0; clock2 = 0;
  forever begin
      #5 clock1 = 1;
      #5 clock1 = 0;
      #5 clock2 = 1;
      #5 clock2 = 0;
  end
end

initial 
begin
  computer.instruction_memory[0]=570425352;
  computer.instruction_memory[1]=587202561;
  computer.instruction_memory[2]=2433810432;
  computer.instruction_memory[3]=2433810432;
  computer.instruction_memory[4]=2433810432;
  computer.instruction_memory[5]=2433810432;
  computer.instruction_memory[6]=3523215364;
  computer.instruction_memory[7]=1109393408;
  computer.instruction_memory[8]=1646460928;
  computer.instruction_memory[9]=4026597369;
  computer.instruction_memory[10]=2433810432;
  computer.instruction_memory[11]=2433810432;
  computer.instruction_memory[12]=2433810432;
  computer.instruction_memory[13]=2433810432;
  computer.instruction_memory[14]=553648131;
  computer.instruction_memory[15]=2433810432;
  computer.instruction_memory[16]=2433810432;
  computer.instruction_memory[17]=2433810432;
  computer.instruction_memory[18]=2433810432;
  computer.instruction_memory[19]=2433810432;
  computer.instruction_memory[20]=823132162;
  computer.instruction_memory[21]=0;

end

initial
begin
  $dumpfile("test_memory.vcd");
  $dumpvars(0, test_memory);
end

initial
begin
  $monitor("PC = %2d, mem[1] = %2d, mem[2] = %2d, mem[3] = %2d, mem[4] = %2d, mem[5] = %2d, mem[6] = %2d, mem[7] = %2d, mem[8] = %2d. Fetch test: mem[5] = %2d.", 
    computer.if_pc, computer.data_memory[1], computer.data_memory[2],  computer.data_memory[3], computer.data_memory[4],
    computer.data_memory[5], computer.data_memory[6], computer.data_memory[7], computer.data_memory[8], computer.register_bank[1]);
  #2000 $finish;
end

endmodule

processor/tests/memory/test_memory.vcd
$date
	Sun May 26 22:23:00 2024
$end
$version
	Icarus Verilog
$end
$timescale
	1s
$end
$scope module test_memory $end
$var reg 1 ! clock1 $end
$var reg 1 " clock2 $end
$scope module computer $end
$var wire 1 ! clock1 $end
$var wire 1 " clock2 $end
$var parameter 4 # ADD $end
$var parameter 4 $ AND $end
$var parameter 4 % GTR $end
$var parameter 4 & HLT $end
$var parameter 4 ' JEZ $end
$var parameter 4 ( JMP $end
$var parameter 4 ) JNZ $end
$var parameter 4 * LES $end
$var parameter 4 + LOD $end
$var parameter 4 , MOV $end
$var parameter 4 - MUL $end
$var parameter 4 . MVI $end
$var parameter 4 / NOT $end
$var parameter 4 0 ORR $end
$var parameter 4 1 STR $end
$var parameter 4 2 SUB $end
$var reg 32 3 ex_alu_result [31:0] $end
$var reg 1 4 ex_has_result $end
$var reg 32 5 ex_immediate [31:0] $end
$var reg 1 6 ex_invalid $end
$var reg 4 7 ex_opcode [3:0] $end
$var reg 32 8 ex_pc [31:0] $end
$var reg 4 9 ex_ra [3:0] $end
$var reg 32 : ex_ra_val [31:0] $end
$var reg 4 ; ex_rb [3:0] $end
$var reg 32 < ex_rb_val [31:0] $end
$var reg 4 = ex_rdest [3:0] $end
$var reg 32 > ex_rdest_val [31:0] $end
$var reg 32 ? id_immediate [31:0] $end
$var reg 1 @ id_invalid $end
$var reg 4 A id_opcode [3:0] $end
$var reg 32 B id_pc [31:0] $end
$var reg 4 C id_ra [3:0] $end
$var reg 32 D id_ra_val [31:0] $end
$var reg 4 E id_rb [3:0] $end
$var reg 32 F id_rb_val [31:0] $end
$var reg 4 G id_rdest [3:0] $end
$var reg 32 H id_rdest_val [31:0] $end
$var reg 1 I if_branch_taken $end
$var reg 1 J if_halted $end
$var reg 32 K if_ir [31:0] $end
$var reg 1 L if_next_branch_taken $end
$var reg 32 M if_next_pc [31:0] $end
$var reg 32 N if_pc [31:0] $end
$var reg 32 O ma_alu_result [31:0] $end
$var reg 1 P ma_has_result $end
$var reg 32 Q ma_immediate [31:0] $end
$var reg 1 R ma_invalid $end
$var reg 4 S ma_opcode [3:0] $end
$var reg 4 T ma_ra [3:0] $end
$var reg 32 U ma_ra_val [31:0] $end
$var reg 4 V ma_rb [3:0] $end
$var reg 4 W ma_rdest [3:0] $end
$upscope $end
$upscope $end
$enddefinitions $end
$comment Show the parameter values. $end
$dumpall
b110 2
b100 1
b1001 0
b1010 /
b10 .
b111 -
b1 ,
b11 +
b1011 *
b1110 )
b1111 (
b1101 '
b0 &
b1100 %
b1000 $
b101 #
$end
#0
$dumpvars
bx W
bx V
bx U
bx T
bx S
1R
bx Q
xP
bx O
bx N
b0 M
0L
bx K
0J
xI
bx H
bx G
bx F
bx E
bx D
bx C
bx B
bx A
1@
bx ?
bx >
bx =
bx <
bx ;
bx :
bx 9
bx 8
bx 7
16
bx 5
x4
bx 3
0"
0!
$end
#5
1!
#7
b1 M
b100010000000000000000000001000 K
0I
b0 N
#10
0!
#15
0@
b0 B
b1000 ?
b0 E
b0 C
b10 G
b10 A
1"
#20
0"
#25
b1000 5
b0 ;
b0 9
b10 =
b0 8
b10 7
06
1!
#27
b10 M
b100011000000000000000000000001 K
b1 N
#30
0!
#35
b1000 Q
b0 V
b0 T
b10 W
b10 S
0R
b1 B
b1 ?
b11 G
1"
#40
0"
#45
b1 5
b11 =
b1 8
1!
#47
b11 M
b10010001000100010000000000000000 K
b10 N
#50
0!
#55
b10 B
b0 ?
b1 E
b1 C
b1 G
b1001 A
b1 Q
b11 W
1"
#60
0"
#65
14
b0 5
b1 ;
b1 9
b1 =
b10 8
b1001 7
1!
#67
b100 M
b11 N
#70
0!
#75
1P
b0 Q
b1 V
b1 T
b1 W
b1001 S
b11 B
1"
#80
0"
#85
b11 8
1!
#87
b101 M
b100 N
#90
0!
#95
b100 B
1"
#100
0"
#105
b100 8
1!
#107
b110 M
b101 N
#110
0!
#115
b101 B
1"
#120
0"
#125
b101 8
1!
#127
b111 M
b11010010000000000000000000000100 K
b110 N
#130
0!
#135
b110 B
b100 ?
b1000 H
b0 E
b0 C
b10 G
b1101 A
1"
#140
0"
#145
04
b100 5
b1000 >
b0 ;
b0 9
b10 =
b110 8
b1101 7
1!
#147
b1000 M
b1000010001000000000000000000000 K
b111 N
#150
0!
#155
0P
b100 Q
b0 V
b0 T
b10 W
b1101 S
b111 B
b0 ?
b1000 D
b10 C
b100 A
1"
#160
0"
#165
b0 5
b1000 :
b10 9
b111 8
b100 7
1!
#167
b1001 M
b1100010001000110000000000000000 K
b1000 N
#170
0!
#175
b1000 B
b1 F
b11 E
b110 A
b0 Q
b1000 U
b10 T
b100 S
1"
#180
0"
#185
b111 3
14
b1 <
b11 ;
b1000 8
b110 7
1!
#187
b1010 M
b11110000000000001111111111111001 K
b1001 N
#190
0!
#195
1P
b111 O
b11 V
b110 S
b1001 B
b11111111111111111111111111111001 ?
bx F
bx D
bx H
b0 E
b0 C
b0 G
b1111 A
1"
#200
0"
#205
b10 M
1L
04
b11111111111111111111111111111001 5
bx <
bx :
bx >
b0 ;
b0 9
b0 =
b1001 8
b1111 7
1!
#207
b11 M
0L
b10010001000100010000000000000000 K
1I
b10 N
#210
0!
#215
1@
b10 B
b0 ?
b1 E
b1 C
b1 G
b1001 A
0P
b11111111111111111111111111111001 Q
bx U
b0 V
b0 T
b0 W
b1111 S
1"
#220
0"
#225
16
1!
#227
b100 M
0I
b11 N
#230
0!
#235
1R
0@
b11 B
1"
#240
0"
#245
bx 3
14
b0 5
b1 ;
b1 9
b1 =
b11 8
b1001 7
06
1!
#247
b101 M
b100 N
#250
0!
#255
b100 B
1P
bx O
b0 Q
b1 V
b1 T
b1 W
b1001 S
0R
1"
#260
0"
#265
b100 8
1!
#267
b110 M
b101 N
#270
0!
#275
b101 B
1"
#280
0"
#285
b101 8
1!
#287
b111 M
b11010010000000000000000000000100 K
b110 N
#290
0!
#295
b110 B
b100 ?
b111 H
b0 E
b0 C
b10 G
b1101 A
1"
#300
0"
#305
04
b100 5
b111 >
b0 ;
b0 9
b10 =
b110 8
b1101 7
1!
#307
b1000 M
b1000010001000000000000000000000 K
b111 N
#310
0!
#315
0P
b100 Q
b0 V
b0 T
b10 W
b1101 S
b111 B
b0 ?
b111 D
b10 C
b100 A
1"
#320
0"
#325
b0 5
b111 :
b10 9
b111 8
b100 7
1!
#327
b1001 M
b1100010001000110000000000000000 K
b1000 N
#330
0!
#335
b1000 B
b1 F
b11 E
b110 A
b0 Q
b111 U
b10 T
b100 S
1"
#340
0"
#345
b110 3
14
b1 <
b11 ;
b1000 8
b110 7
1!
#347
b1010 M
b11110000000000001111111111111001 K
b1001 N
#350
0!
#355
1P
b110 O
b11 V
b110 S
b1001 B
b11111111111111111111111111111001 ?
bx F
bx D
bx H
b0 E
b0 C
b0 G
b1111 A
1"
#360
0"
#365
b10 M
1L
04
b11111111111111111111111111111001 5
bx <
bx :
bx >
b0 ;
b0 9
b0 =
b1001 8
b1111 7
1!
#367
b11 M
0L
b10010001000100010000000000000000 K
1I
b10 N
#370
0!
#375
1@
b10 B
b0 ?
b1 E
b1 C
b1 G
b1001 A
0P
b11111111111111111111111111111001 Q
bx U
b0 V
b0 T
b0 W
b1111 S
1"
#380
0"
#385
16
1!
#387
b100 M
0I
b11 N
#390
0!
#395
1R
0@
b11 B
1"
#400
0"
#405
bx 3
14
b0 5
b1 ;
b1 9
b1 =
b11 8
b1001 7
06
1!
#407
b101 M
b100 N
#410
0!
#415
b100 B
1P
bx O
b0 Q
b1 V
b1 T
b1 W
b1001 S
0R
1"
#420
0"
#425
b100 8
1!
#427
b110 M
b101 N
#430
0!
#435
b101 B
1"
#440
0"
#445
b101 8
1!
#447
b111 M
b11010010000000000000000000000100 K
b110 N
#450
0!
#455
b110 B
b100 ?
b110 H
b0 E
b0 C
b10 G
b1101 A
1"
#460
0"
#465
04
b100 5
b110 >
b0 ;
b0 9
b10 =
b110 8
b1101 7
1!
#467
b1000 M
b1000010001000000000000000000000 K
b111 N
#470
0!
#475
0P
b100 Q
b0 V
b0 T
b10 W
b1101 S
b111 B
b0 ?
b110 D
b10 C
b100 A
1"
#480
0"
#485
b0 5
b110 :
b10 9
b111 8
b100 7
1!
#487
b1001 M
b1100010001000110000000000000000 K
b1000 N
#490
0!
#495
b1000 B
b1 F
b11 E
b110 A
b0 Q
b110 U
b10 T
b100 S
1"
#500
0"
#505
b101 3
14
b1 <
b11 ;
b1000 8
b110 7
1!
#507
b1010 M
b11110000000000001111111111111001 K
b1001 N
#510
0!
#515
1P
b101 O
b11 V
b110 S
b1001 B
b11111111111111111111111111111001 ?
bx F
bx D
bx H
b0 E
b0 C
b0 G
b1111 A
1"
#520
0"
#525
b10 M
1L
04
b11111111111111111111111111111001 5
bx <
bx :
bx >
b0 ;
b0 9
b0 =
b1001 8
b1111 7
1!
#527
b11 M
0L
b10010001000100010000000000000000 K
1I
b10 N
#530
0!
#535
1@
b10 B
b0 ?
b1 E
b1 C
b1 G
b1001 A
0P
b11111111111111111111111111111001 Q
bx U
b0 V
b0 T
b0 W
b1111 S
1"
#540
0"
#545
16
1!
#547
b100 M
0I
b11 N
#550
0!
#555
1R
0@
b11 B
1"
#560
0"
#565
bx 3
14
b0 5
b1 ;
b1 9
b1 =
b11 8
b1001 7
06
1!
#567
b101 M
b100 N
#570
0!
#575
b100 B
1P
bx O
b0 Q
b1 V
b1 T
b1 W
b1001 S
0R
1"
#580
0"
#585
b100 8
1!
#587
b110 M
b101 N
#590
0!
#595
b101 B
1"
#600
0"
#605
b101 8
1!
#607
b111 M
b11010010000000000000000000000100 K
b110 N
#610
0!
#615
b110 B
b100 ?
b101 H
b0 E
b0 C
b10 G
b1101 A
1"
#620
0"
#625
04
b100 5
b101 >
b0 ;
b0 9
b10 =
b110 8
b1101 7
1!
#627
b1000 M
b1000010001000000000000000000000 K
b111 N
#630
0!
#635
0P
b100 Q
b0 V
b0 T
b10 W
b1101 S
b111 B
b0 ?
b101 D
b10 C
b100 A
1"
#640
0"
#645
b0 5
b101 :
b10 9
b111 8
b100 7
1!
#647
b1001 M
b1100010001000110000000000000000 K
b1000 N
#650
0!
#655
b1000 B
b1 F
b11 E
b110 A
b0 Q
b101 U
b10 T
b100 S
1"
#660
0"
#665
b100 3
14
b1 <
b11 ;
b1000 8
b110 7
1!
#667
b1010 M
b11110000000000001111111111111001 K
b1001 N
#670
0!
#675
1P
b100 O
b11 V
b110 S
b1001 B
b11111111111111111111111111111001 ?
bx F
bx D
bx H
b0 E
b0 C
b0 G
b1111 A
1"
#680
0"
#685
b10 M
1L
04
b11111111111111111111111111111001 5
bx <
bx :
bx >
b0 ;
b0 9
b0 =
b1001 8
b1111 7
1!
#687
b11 M
0L
b10010001000100010000000000000000 K
1I
b10 N
#690
0!
#695
1@
b10 B
b0 ?
b1 E
b1 C
b1 G
b1001 A
0P
b11111111111111111111111111111001 Q
bx U
b0 V
b0 T
b0 W
b1111 S
1"
#700
0"
#705
16
1!
#707
b100 M
0I
b11 N
#710
0!
#715
1R
0@
b11 B
1"
#720
0"
#725
bx 3
14
b0 5
b1 ;
b1 9
b1 =
b11 8
b1001 7
06
1!
#727
b101 M
b100 N
#730
0!
#735
b100 B
1P
bx O
b0 Q
b1 V
b1 T
b1 W
b1001 S
0R
1"
#740
0"
#745
b100 8
1!
#747
b110 M
b101 N
#750
0!
#755
b101 B
1"
#760
0"
#765
b101 8
1!
#767
b111 M
b11010010000000000000000000000100 K
b110 N
#770
0!
#775
b110 B
b100 ?
b100 H
b0 E
b0 C
b10 G
b1101 A
1"
#780
0"
#785
04
b100 5
b100 >
b0 ;
b0 9
b10 =
b110 8
b1101 7
1!
#787
b1000 M
b1000010001000000000000000000000 K
b111 N
#790
0!
#795
0P
b100 Q
b0 V
b0 T
b10 W
b1101 S
b111 B
b0 ?
b100 D
b10 C
b100 A
1"
#800
0"
#805
b0 5
b100 :
b10 9
b111 8
b100 7
1!
#807
b1001 M
b1100010001000110000000000000000 K
b1000 N
#810
0!
#815
b1000 B
b1 F
b11 E
b110 A
b0 Q
b100 U
b10 T
b100 S
1"
#820
0"
#825
b11 3
14
b1 <
b11 ;
b1000 8
b110 7
1!
#827
b1010 M
b11110000000000001111111111111001 K
b1001 N
#830
0!
#835
1P
b11 O
b11 V
b110 S
b1001 B
b11111111111111111111111111111001 ?
bx F
bx D
bx H
b0 E
b0 C
b0 G
b1111 A
1"
#840
0"
#845
b10 M
1L
04
b11111111111111111111111111111001 5
bx <
bx :
bx >
b0 ;
b0 9
b0 =
b1001 8
b1111 7
1!
#847
b11 M
0L
b10010001000100010000000000000000 K
1I
b10 N
#850
0!
#855
1@
b10 B
b0 ?
b1 E
b1 C
b1 G
b1001 A
0P
b11111111111111111111111111111001 Q
bx U
b0 V
b0 T
b0 W
b1111 S
1"
#860
0"
#865
16
1!
#867
b100 M
0I
b11 N
#870
0!
#875
1R
0@
b11 B
1"
#880
0"
#885
bx 3
14
b0 5
b1 ;
b1 9
b1 =
b11 8
b1001 7
06
1!
#887
b101 M
b100 N
#890
0!
#895
b100 B
1P
bx O
b0 Q
b1 V
b1 T
b1 W
b1001 S
0R
1"
#900
0"
#905
b100 8
1!
#907
b110 M
b101 N
#910
0!
#915
b101 B
1"
#920
0"
#925
b101 8
1!
#927
b111 M
b11010010000000000000000000000100 K
b110 N
#930
0!
#935
b110 B
b100 ?
b11 H
b0 E
b0 C
b10 G
b1101 A
1"
#940
0"
#945
04
b100 5
b11 >
b0 ;
b0 9
b10 =
b110 8
b1101 7
1!
#947
b1000 M
b1000010001000000000000000000000 K
b111 N
#950
0!
#955
0P
b100 Q
b0 V
b0 T
b10 W
b1101 S
b111 B
b0 ?
b11 D
b10 C
b100 A
1"
#960
0"
#965
b0 5
b11 :
b10 9
b111 8
b100 7
1!
#967
b1001 M
b1100010001000110000000000000000 K
b1000 N
#970
0!
#975
b1000 B
b1 F
b11 E
b110 A
b0 Q
b11 U
b10 T
b100 S
1"
#980
0"
#985
b10 3
14
b1 <
b11 ;
b1000 8
b110 7
1!
#987
b1010 M
b11110000000000001111111111111001 K
b1001 N
#990
0!
#995
1P
b10 O
b11 V
b110 S
b1001 B
b11111111111111111111111111111001 ?
bx F
bx D
bx H
b0 E
b0 C
b0 G
b1111 A
1"
#1000
0"
#1005
b10 M
1L
04
b11111111111111111111111111111001 5
bx <
bx :
bx >
b0 ;
b0 9
b0 =
b1001 8
b1111 7
1!
#1007
b11 M
0L
b10010001000100010000000000000000 K
1I
b10 N
#1010
0!
#1015
1@
b10 B
b0 ?
b1 E
b1 C
b1 G
b1001 A
0P
b11111111111111111111111111111001 Q
bx U
b0 V
b0 T
b0 W
b1111 S
1"
#1020
0"
#1025
16
1!
#1027
b100 M
0I
b11 N
#1030
0!
#1035
1R
0@
b11 B
1"
#1040
0"
#1045
bx 3
14
b0 5
b1 ;
b1 9
b1 =
b11 8
b1001 7
06
1!
#1047
b101 M
b100 N
#1050
0!
#1055
b100 B
1P
bx O
b0 Q
b1 V
b1 T
b1 W
b1001 S
0R
1"
#1060
0"
#1065
b100 8
1!
#1067
b110 M
b101 N
#1070
0!
#1075
b101 B
1"
#1080
0"
#1085
b101 8
1!
#1087
b111 M
b11010010000000000000000000000100 K
b110 N
#1090
0!
#1095
b110 B
b100 ?
b10 H
b0 E
b0 C
b10 G
b1101 A
1"
#1100
0"
#1105
04
b100 5
b10 >
b0 ;
b0 9
b10 =
b110 8
b1101 7
1!
#1107
b1000 M
b1000010001000000000000000000000 K
b111 N
#1110
0!
#1115
0P
b100 Q
b0 V
b0 T
b10 W
b1101 S
b111 B
b0 ?
b10 D
b10 C
b100 A
1"
#1120
0"
#1125
b0 5
b10 :
b10 9
b111 8
b100 7
1!
#1127
b1001 M
b1100010001000110000000000000000 K
b1000 N
#1130
0!
#1135
b1000 B
b1 F
b11 E
b110 A
b0 Q
b10 U
b10 T
b100 S
1"
#1140
0"
#1145
b1 3
14
b1 <
b11 ;
b1000 8
b110 7
1!
#1147
b1010 M
b11110000000000001111111111111001 K
b1001 N
#1150
0!
#1155
1P
b1 O
b11 V
b110 S
b1001 B
b11111111111111111111111111111001 ?
bx F
bx D
bx H
b0 E
b0 C
b0 G
b1111 A
1"
#1160
0"
#1165
b10 M
1L
04
b11111111111111111111111111111001 5
bx <
bx :
bx >
b0 ;
b0 9
b0 =
b1001 8
b1111 7
1!
#1167
b11 M
0L
b10010001000100010000000000000000 K
1I
b10 N
#1170
0!
#1175
1@
b10 B
b0 ?
b1 E
b1 C
b1 G
b1001 A
0P
b11111111111111111111111111111001 Q
bx U
b0 V
b0 T
b0 W
b1111 S
1"
#1180
0"
#1185
16
1!
#1187
b100 M
0I
b11 N
#1190
0!
#1195
1R
0@
b11 B
1"
#1200
0"
#1205
bx 3
14
b0 5
b1 ;
b1 9
b1 =
b11 8
b1001 7
06
1!
#1207
b101 M
b100 N
#1210
0!
#1215
b100 B
1P
bx O
b0 Q
b1 V
b1 T
b1 W
b1001 S
0R
1"
#1220
0"
#1225
b100 8
1!
#1227
b110 M
b101 N
#1230
0!
#1235
b101 B
1"
#1240
0"
#1245
b101 8
1!
#1247
b111 M
b11010010000000000000000000000100 K
b110 N
#1250
0!
#1255
b110 B
b100 ?
b1 H
b0 E
b0 C
b10 G
b1101 A
1"
#1260
0"
#1265
04
b100 5
b1 >
b0 ;
b0 9
b10 =
b110 8
b1101 7
1!
#1267
b1000 M
b1000010001000000000000000000000 K
b111 N
#1270
0!
#1275
0P
b100 Q
b0 V
b0 T
b10 W
b1101 S
b111 B
b0 ?
b1 D
b10 C
b100 A
1"
#1280
0"
#1285
b0 5
b1 :
b10 9
b111 8
b100 7
1!
#1287
b1001 M
b1100010001000110000000000000000 K
b1000 N
#1290
0!
#1295
b1000 B
b1 F
b11 E
b110 A
b0 Q
b1 U
b10 T
b100 S
1"
#1300
0"
#1305
b0 3
14
b1 <
b11 ;
b1000 8
b110 7
1!
#1307
b1010 M
b11110000000000001111111111111001 K
b1001 N
#1310
0!
#1315
1P
b0 O
b11 V
b110 S
b1001 B
b11111111111111111111111111111001 ?
bx F
bx D
bx H
b0 E
b0 C
b0 G
b1111 A
1"
#1320
0"
#1325
b10 M
1L
04
b11111111111111111111111111111001 5
bx <
bx :
bx >
b0 ;
b0 9
b0 =
b1001 8
b1111 7
1!
#1327
b11 M
0L
b10010001000100010000000000000000 K
1I
b10 N
#1330
0!
#1335
1@
b10 B
b0 ?
b1 E
b1 C
b1 G
b1001 A
0P
b11111111111111111111111111111001 Q
bx U
b0 V
b0 T
b0 W
b1111 S
1"
#1340
0"
#1345
16
1!
#1347
b100 M
0I
b11 N
#1350
0!
#1355
1R
0@
b11 B
1"
#1360
0"
#1365
bx 3
14
b0 5
b1 ;
b1 9
b1 =
b11 8
b1001 7
06
1!
#1367
b101 M
b100 N
#1370
0!
#1375
b100 B
1P
bx O
b0 Q
b1 V
b1 T
b1 W
b1001 S
0R
1"
#1380
0"
#1385
b100 8
1!
#1387
b110 M
b101 N
#1390
0!
#1395
b101 B
1"
#1400
0"
#1405
b101 8
1!
#1407
b111 M
b11010010000000000000000000000100 K
b110 N
#1410
0!
#1415
b110 B
b100 ?
b0 H
b0 E
b0 C
b10 G
b1101 A
1"
#1420
0"
#1425
b1010 M
1L
04
b100 5
b0 >
b0 ;
b0 9
b10 =
b110 8
b1101 7
1!
#1427
b1011 M
0L
b10010001000100010000000000000000 K
1I
b1010 N
#1430
0!
