processor/processor.v
module processor(clock1, clock2);
  // 2-phase clocks:
  // - for controlled operations in each pipeline stage
  // With a single clock activating all stages at once, the successive
  // pipeline stages can work incorrectly if the input for one stage doesn't
  // arrive in time from the previous stage.
  // With 2-phase clocks each adjacent stages will be activated alternately
  // avoid this scenerio
  input clock1, clock2;

  reg [31:0] register_bank [0:15];
  reg [31:0] instruction_memory [0:1023];
  reg [31:0] data_memory [0:1023];

  // opcodes
  parameter 
    HLT = 4'b0000,
    MOV = 4'b0001,
    MVI = 4'b0010,
    LOD = 4'b0011,
    STR = 4'b0100,
    ADD = 4'b0101,
    SUB = 4'b0110,
    MUL = 4'b0111,
    AND = 4'b1000,
    ORR = 4'b1001,
    NOT = 4'b1010,
    LES = 4'b1011,
    GTR = 4'b1100,
    JEZ = 4'b1101,
    JNZ = 4'b1110,
    JMP = 4'b1111;

    

  // ----- instruction fetch (if) stage -----
  
  // states
  reg [31:0] if_pc, if_next_pc, if_ir;
  reg if_halted, if_branch_taken, if_next_branch_taken;

  initial
  begin
    if_halted <= 0;
    if_next_pc <= 0;
    if_next_branch_taken <= 0;
    id_invalid <= 1;
    ex_invalid <= 1;
    ma_invalid <= 1;
  end
  
  always @ (posedge clock1) 
  begin
    // if and ex stages are activated by the same clock 
    // so waiting some time to let the branch and halted signals from ex
    // stage come in
    #2;
    if (if_halted == 0)
    begin
      if_pc = if_next_pc;
      if_branch_taken = if_next_branch_taken;
      if (if_branch_taken == 1)
      begin
        if_ir = instruction_memory[if_pc];
        if_next_branch_taken = 0;
        if_next_pc = if_pc + 1;
      end
      else 
      begin
        if_ir = instruction_memory[if_pc];
        if_next_pc = if_pc + 1;
      end
    end
  end



  // ----- instruction decode (id) stage -----

  // states
  reg [3:0] id_opcode, id_rdest, id_ra, id_rb;
  reg [31:0] id_pc, id_rdest_val, id_ra_val, id_rb_val, id_immediate;
  reg id_invalid; // due to branch jump or program being halted, the instruction in this stage of pipeline can be invalid

  always @ (posedge clock2)
  begin 
    // instruction decoding
    id_opcode <= if_ir[31:28];
    id_rdest <= if_ir[27:24];
    id_ra <= if_ir[23:20];
    id_rb <= if_ir[19:16];
    id_rdest_val <= register_bank[if_ir[27:24]]; // register prefetching
    id_ra_val <= register_bank[if_ir[23:20]];
    id_rb_val <= register_bank[if_ir[19:16]];
    // 16-bit signed immediate number need to be converted to 32-bits
    // for that the signed bit needs to be copied as 16-MSBs
    id_immediate <= {{16{if_ir[15]}}, {if_ir[15:0]}};

    id_pc <= if_pc;
    id_invalid <= (if_branch_taken | if_halted) ? 1: 0;
  end




  // ----- execute (ex) stage: ALU and branch instruction execution -----

  // states
  reg [3:0] ex_opcode, ex_rdest, ex_ra, ex_rb;
  reg [31:0] ex_alu_result, ex_pc, ex_rdest_val, ex_ra_val, ex_rb_val, ex_immediate;
  reg ex_invalid, ex_has_result;


  always @ (posedge clock1) 
  begin
    if (id_invalid == 0) 
    begin
      ex_invalid <= 0;
      ex_opcode <= id_opcode;
      ex_pc <= id_pc;
      ex_rdest <= id_rdest;
      ex_ra <= id_ra;
      ex_rb <= id_rb;
      ex_rdest_val <= id_rdest_val;
      ex_ra_val <= id_ra_val;
      ex_rb_val <= id_rb_val;
      ex_immediate <= id_immediate;
      case (id_opcode)
        ADD: begin ex_has_result <= 1; ex_alu_result <= id_ra_val + id_rb_val; end
        SUB: begin ex_has_result <= 1; ex_alu_result <= id_ra_val - id_rb_val; end
        MUL: begin ex_has_result <= 1; ex_alu_result <= id_ra_val * id_rb_val; end
        AND: begin ex_has_result <= 1; ex_alu_result <= id_ra_val & id_rb_val; end
        ORR: begin ex_has_result <= 1; ex_alu_result <= id_ra_val | id_rb_val; end
        NOT: begin ex_has_result <= 1; ex_alu_result <= ~id_ra_val; end
        LES: begin ex_has_result <= 1; ex_alu_result <= (id_ra_val < id_rb_val) ? 1 : 0; end
        GTR: begin ex_has_result <= 1; ex_alu_result <= (id_ra_val > id_rb_val) ? 1 : 0; end
        JEZ: begin
          ex_has_result <= 0;
          if (id_rdest_val == 0) begin
            if_next_branch_taken <= 1;
            if_next_pc <= id_pc + id_immediate; // pc = pc + offset
          end
        end
        JNZ: begin
          ex_has_result <= 0;
          if (id_rdest_val != 0) begin
            if_next_branch_taken <= 1;
            if_next_pc <= id_pc + id_immediate; // pc = pc + offset
          end
        end
        JMP: begin
          ex_has_result <= 0;
          begin
            if_next_branch_taken <= 1;
            if_next_pc <= id_pc + id_immediate; // pc = pc + offset
          end
        end
        HLT: begin ex_has_result <= 0; if_halted <= 1; end
      endcase
    end
    else ex_invalid <= 1;
  end



  // ----- memory access (ma) stage: memory store and load instruction execution -----

  // states
  reg [3:0] ma_opcode, ma_rdest, ma_ra, ma_rb;
  reg [31:0] ma_alu_result, ma_ra_val, ma_immediate;
  reg ma_invalid, ma_has_result;
  
  always @ (posedge clock2)
  begin
    if (ex_invalid == 0)
    begin
      ma_invalid <= 0;
      ma_opcode <= ex_opcode;
      ma_rdest <= ex_rdest;
      ma_ra <= ex_ra;
      ma_rb <= ex_rb;
      ma_ra_val <= ex_ra_val;
      ma_immediate <= ex_immediate;
      ma_alu_result <= ex_alu_result;
      ma_has_result <= ex_has_result;
      case (ex_opcode)
        LOD: register_bank[ex_rdest] <= data_memory[ex_ra_val + ex_immediate];
        STR: data_memory[ex_ra_val + ex_immediate] <= register_bank[ex_rdest];
      endcase
    end
    else ma_invalid <= 1;
  end



  // ----- write-back (wb) stage: register move instr. + ALU result writeback

  always @ (posedge clock1)
  begin
    if (ma_invalid == 0)
    begin
      if (ma_has_result == 1) begin 
        register_bank[ma_rdest] <= ma_alu_result;
      end
      case (ma_opcode)
        MOV: register_bank[ma_rdest] <= ma_ra_val;
        MVI: register_bank[ma_rdest] <= ma_immediate;
      endcase
    end
  end


endmodule

processor/tests/factorial/test_factorial.v
/*
Assembling factorial/factorial.s ---

---------------------------  debug info  ---------------------------
   #0             MVI R1, 1           0010 0001 0000 0000 0000000000000001
   #1             MVI R2, 5           0010 0010 0000 0000 0000000000000101
   #2             MVI R3, 1           0010 0011 0000 0000 0000000000000001
   #3      :loop  ORR R1, R1, R1      1001 0001 0001 0001 0000000000000000
   #4             ORR R1, R1, R1      1001 0001 0001 0001 0000000000000000
   #5             ORR R1, R1, R1      1001 0001 0001 0001 0000000000000000
   #6             ORR R1, R1, R1      1001 0001 0001 0001 0000000000000000
   #7             GTR R4, R2, R3      1100 0100 0010 0011 0000000000000000
   #8             ORR R1, R1, R1      1001 0001 0001 0001 0000000000000000
   #9             ORR R1, R1, R1      1001 0001 0001 0001 0000000000000000
  #10             ORR R1, R1, R1      1001 0001 0001 0001 0000000000000000
  #11             ORR R1, R1, R1      1001 0001 0001 0001 0000000000000000
  #12             JEZ R4, end         1101 0100 0000 0000 0000000000000100
  #13             MUL R1, R1, R2      0111 0001 0001 0010 0000000000000000
  #14             SUB R2, R2, R3      0110 0010 0010 0011 0000000000000000
  #15             JMP loop            1111 0000 0000 0000 1111111111110100
  #16       :end  HLT                 0000 0000 0000 0000 0000000000000000

----- assembled instructions -------
553648129
570425349
587202561
2433810432
2433810432
2433810432
2433810432
3290628096
2433810432
2433810432
2433810432
2433810432
3556769796
1897005056
1646460928
4026597364
0

----- generated code -------
computer.instruction_memory[0]=553648129;
computer.instruction_memory[1]=570425349;
computer.instruction_memory[2]=587202561;
computer.instruction_memory[3]=2433810432;
computer.instruction_memory[4]=2433810432;
computer.instruction_memory[5]=2433810432;
computer.instruction_memory[6]=2433810432;
computer.instruction_memory[7]=3290628096;
computer.instruction_memory[8]=2433810432;
computer.instruction_memory[9]=2433810432;
computer.instruction_memory[10]=2433810432;
computer.instruction_memory[11]=2433810432;
computer.instruction_memory[12]=3556769796;
computer.instruction_memory[13]=1897005056;
computer.instruction_memory[14]=1646460928;
computer.instruction_memory[15]=4026597364;
computer.instruction_memory[16]=0;

*/

module test_factorial;
reg clock1, clock2;

processor computer(clock1, clock2);

// generate 2-phase clock
initial
begin
  clock1 = 0; clock2 = 0;
  forever begin
      #5 clock1 = 1;
      #5 clock1 = 0;
      #5 clock2 = 1;
      #5 clock2 = 0;
  end
end

initial 
begin
  computer.instruction_memory[0]=553648129;
  computer.instruction_memory[1]=570425349;
  computer.instruction_memory[2]=587202561;
  computer.instruction_memory[3]=2433810432;
  computer.instruction_memory[4]=2433810432;
  computer.instruction_memory[5]=2433810432;
  computer.instruction_memory[6]=2433810432;
  computer.instruction_memory[7]=3290628096;
  computer.instruction_memory[8]=2433810432;
  computer.instruction_memory[9]=2433810432;
  computer.instruction_memory[10]=2433810432;
  computer.instruction_memory[11]=2433810432;
  computer.instruction_memory[12]=3556769796;
  computer.instruction_memory[13]=1897005056;
  computer.instruction_memory[14]=1646460928;
  computer.instruction_memory[15]=4026597364;
  computer.instruction_memory[16]=0;
 
end

initial
begin
  $dumpfile("test_factorial.vcd");
  $dumpvars(0, test_factorial);
end

initial
begin
  $monitor("calculating factorial(5). 5! converging to %3d", computer.register_bank[1]);
  #1200 $finish;
end

endmodule

processor/tests/factorial/test_factorial.vcd
$date
	Sun May 26 20:54:17 2024
$end
$version
	Icarus Verilog
$end
$timescale
	1s
$end
$scope module test_factorial $end
$var reg 1 ! clock1 $end
$var reg 1 " clock2 $end
$scope module computer $end
$var wire 1 ! clock1 $end
$var wire 1 " clock2 $end
$var parameter 4 # ADD $end
$var parameter 4 $ AND $end
$var parameter 4 % GTR $end
$var parameter 4 & HLT $end
$var parameter 4 ' JEZ $end
$var parameter 4 ( JMP $end
$var parameter 4 ) JNZ $end
$var parameter 4 * LES $end
$var parameter 4 + LOD $end
$var parameter 4 , MOV $end
$var parameter 4 - MUL $end
$var parameter 4 . MVI $end
$var parameter 4 / NOT $end
$var parameter 4 0 ORR $end
$var parameter 4 1 STR $end
$var parameter 4 2 SUB $end
$var reg 32 3 ex_alu_result [31:0] $end
$var reg 1 4 ex_has_result $end
$var reg 32 5 ex_immediate [31:0] $end
$var reg 1 6 ex_invalid $end
$var reg 4 7 ex_opcode [3:0] $end
$var reg 32 8 ex_pc [31:0] $end
$var reg 4 9 ex_ra [3:0] $end
$var reg 32 : ex_ra_val [31:0] $end
$var reg 4 ; ex_rb [3:0] $end
$var reg 32 < ex_rb_val [31:0] $end
$var reg 4 = ex_rdest [3:0] $end
$var reg 32 > ex_rdest_val [31:0] $end
$var reg 32 ? id_immediate [31:0] $end
$var reg 1 @ id_invalid $end
$var reg 4 A id_opcode [3:0] $end
$var reg 32 B id_pc [31:0] $end
$var reg 4 C id_ra [3:0] $end
$var reg 32 D id_ra_val [31:0] $end
$var reg 4 E id_rb [3:0] $end
$var reg 32 F id_rb_val [31:0] $end
$var reg 4 G id_rdest [3:0] $end
$var reg 32 H id_rdest_val [31:0] $end
$var reg 1 I if_branch_taken $end
$var reg 1 J if_halted $end
$var reg 32 K if_ir [31:0] $end
$var reg 1 L if_next_branch_taken $end
$var reg 32 M if_next_pc [31:0] $end
$var reg 32 N if_pc [31:0] $end
$var reg 32 O ma_alu_result [31:0] $end
$var reg 1 P ma_has_result $end
$var reg 32 Q ma_immediate [31:0] $end
$var reg 1 R ma_invalid $end
$var reg 4 S ma_opcode [3:0] $end
$var reg 4 T ma_ra [3:0] $end
$var reg 32 U ma_ra_val [31:0] $end
$var reg 4 V ma_rb [3:0] $end
$var reg 4 W ma_rdest [3:0] $end
$upscope $end
$upscope $end
$enddefinitions $end
$comment Show the parameter values. $end
$dumpall
b110 2
b100 1
b1001 0
b1010 /
b10 .
b111 -
b1 ,
b11 +
b1011 *
b1110 )
b1111 (
b1101 '
b0 &
b1100 %
b1000 $
b101 #
$end
#0
$dumpvars
bx W
bx V
bx U
bx T
bx S
1R
bx Q
xP
bx O
bx N
b0 M
0L
bx K
0J
xI
bx H
bx G
bx F
bx E
bx D
bx C
bx B
bx A
1@
bx ?
bx >
bx =
bx <
bx ;
bx :
bx 9
bx 8
bx 7
16
bx 5
x4
bx 3
0"
0!
$end
#5
1!
#7
b1 M
b100001000000000000000000000001 K
0I
b0 N
#10
0!
#15
0@
b0 B
b1 ?
b0 E
b0 C
b1 G
b10 A
1"
#20
0"
#25
b1 5
b0 ;
b0 9
b1 =
b0 8
b10 7
06
1!
#27
b10 M
b100010000000000000000000000101 K
b1 N
#30
0!
#35
b1 Q
b0 V
b0 T
b1 W
b10 S
0R
b1 B
b101 ?
b10 G
1"
#40
0"
#45
b101 5
b10 =
b1 8
1!
#47
b11 M
b100011000000000000000000000001 K
b10 N
#50
0!
#55
b10 B
b1 ?
b11 G
b101 Q
b10 W
1"
#60
0"
#65
b1 5
b11 =
b10 8
1!
#67
b100 M
b10010001000100010000000000000000 K
b11 N
#70
0!
#75
b1 Q
b11 W
b11 B
b0 ?
b1 F
b1 D
b1 H
b1 E
b1 C
b1 G
b1001 A
1"
#80
0"
#85
b1 3
14
b0 5
b1 <
b1 :
b1 >
b1 ;
b1 9
b1 =
b11 8
b1001 7
1!
#87
b101 M
b100 N
#90
0!
#95
b100 B
1P
b1 O
b0 Q
b1 U
b1 V
b1 T
b1 W
b1001 S
1"
#100
0"
#105
b100 8
1!
#107
b110 M
b101 N
#110
0!
#115
b101 B
1"
#120
0"
#125
b101 8
1!
#127
b111 M
b110 N
#130
0!
#135
b110 B
1"
#140
0"
#145
b110 8
1!
#147
b1000 M
b11000100001000110000000000000000 K
b111 N
#150
0!
#155
b111 B
b101 D
bx H
b11 E
b10 C
b100 G
b1100 A
1"
#160
0"
#165
b101 :
bx >
b11 ;
b10 9
b100 =
b111 8
b1100 7
1!
#167
b1001 M
b10010001000100010000000000000000 K
b1000 N
#170
0!
#175
b1000 B
b1 D
b1 H
b1 E
b1 C
b1 G
b1001 A
b101 U
b11 V
b10 T
b100 W
b1100 S
1"
#180
0"
#185
b1 :
b1 >
b1 ;
b1 9
b1 =
b1000 8
b1001 7
1!
#187
b1010 M
b1001 N
#190
0!
#195
b1 U
b1 V
b1 T
b1 W
b1001 S
b1001 B
1"
#200
0"
#205
b1001 8
1!
#207
b1011 M
b1010 N
#210
0!
#215
b1010 B
1"
#220
0"
#225
b1010 8
1!
#227
b1100 M
b1011 N
#230
0!
#235
b1011 B
1"
#240
0"
#245
b1011 8
1!
#247
b1101 M
b11010100000000000000000000000100 K
b1100 N
#250
0!
#255
b1100 B
b100 ?
bx F
bx D
b0 E
b0 C
b100 G
b1101 A
1"
#260
0"
#265
04
b100 5
bx <
bx :
b0 ;
b0 9
b100 =
b1100 8
b1101 7
1!
#267
b1110 M
b1110001000100100000000000000000 K
b1101 N
#270
0!
#275
0P
b100 Q
bx U
b0 V
b0 T
b100 W
b1101 S
b1101 B
b0 ?
b101 F
b1 D
b10 E
b1 C
b1 G
b111 A
1"
#280
0"
#285
b101 3
14
b0 5
b101 <
b1 :
b10 ;
b1 9
b1 =
b1101 8
b111 7
1!
#287
b1111 M
b1100010001000110000000000000000 K
b1110 N
#290
0!
#295
b1110 B
b1 F
b101 D
b101 H
b11 E
b10 C
b10 G
b110 A
1P
b101 O
b0 Q
b1 U
b10 V
b1 T
b1 W
b111 S
1"
#300
0"
#305
b100 3
b1 <
b101 :
b101 >
b11 ;
b10 9
b10 =
b1110 8
b110 7
1!
#307
b10000 M
b11110000000000001111111111110100 K
b1111 N
#310
0!
#315
b100 O
b101 U
b11 V
b10 T
b10 W
b110 S
b1111 B
b11111111111111111111111111110100 ?
bx F
bx D
bx H
b0 E
b0 C
b0 G
b1111 A
1"
#320
0"
#325
b11 M
1L
04
b11111111111111111111111111110100 5
bx <
bx :
bx >
b0 ;
b0 9
b0 =
b1111 8
b1111 7
1!
#327
b100 M
0L
b10010001000100010000000000000000 K
1I
b11 N
#330
0!
#335
1@
b11 B
b0 ?
b101 F
b101 D
b101 H
b1 E
b1 C
b1 G
b1001 A
0P
b11111111111111111111111111110100 Q
bx U
b0 V
b0 T
b0 W
b1111 S
1"
#340
0"
#345
16
1!
#347
b101 M
0I
b100 N
#350
0!
#355
1R
0@
b100 B
1"
#360
0"
#365
b101 3
14
b0 5
b101 <
b101 :
b101 >
b1 ;
b1 9
b1 =
b100 8
b1001 7
06
1!
#367
b110 M
b101 N
#370
0!
#375
b101 B
1P
b101 O
b0 Q
b101 U
b1 V
b1 T
b1 W
b1001 S
0R
1"
#380
0"
#385
b101 8
1!
#387
b111 M
b110 N
#390
0!
#395
b110 B
1"
#400
0"
#405
b110 8
1!
#407
b1000 M
b11000100001000110000000000000000 K
b111 N
#410
0!
#415
b111 B
b1 F
b100 D
b1 H
b11 E
b10 C
b100 G
b1100 A
1"
#420
0"
#425
b1 3
b1 <
b100 :
b1 >
b11 ;
b10 9
b100 =
b111 8
b1100 7
1!
#427
b1001 M
b10010001000100010000000000000000 K
b1000 N
#430
0!
#435
b1 O
b100 U
b11 V
b10 T
b100 W
b1100 S
b1000 B
b101 F
b101 D
b101 H
b1 E
b1 C
b1 G
b1001 A
1"
#440
0"
#445
b101 3
b101 <
b101 :
b101 >
b1 ;
b1 9
b1 =
b1000 8
b1001 7
1!
#447
b1010 M
b1001 N
#450
0!
#455
b1001 B
b101 O
b101 U
b1 V
b1 T
b1 W
b1001 S
1"
#460
0"
#465
b1001 8
1!
#467
b1011 M
b1010 N
#470
0!
#475
b1010 B
1"
#480
0"
#485
b1010 8
1!
#487
b1100 M
b1011 N
#490
0!
#495
b1011 B
1"
#500
0"
#505
b1011 8
1!
#507
b1101 M
b11010100000000000000000000000100 K
b1100 N
#510
0!
#515
b1100 B
b100 ?
bx F
bx D
b1 H
b0 E
b0 C
b100 G
b1101 A
1"
#520
0"
#525
04
b100 5
bx <
bx :
b1 >
b0 ;
b0 9
b100 =
b1100 8
b1101 7
1!
#527
b1110 M
b1110001000100100000000000000000 K
b1101 N
#530
0!
#535
b1101 B
b0 ?
b100 F
b101 D
b101 H
b10 E
b1 C
b1 G
b111 A
0P
b100 Q
bx U
b0 V
b0 T
b100 W
b1101 S
1"
#540
0"
#545
b10100 3
14
b0 5
b100 <
b101 :
b101 >
b10 ;
b1 9
b1 =
b1101 8
b111 7
1!
#547
b1111 M
b1100010001000110000000000000000 K
b1110 N
#550
0!
#555
1P
b10100 O
b0 Q
b101 U
b10 V
b1 T
b1 W
b111 S
b1110 B
b1 F
b100 D
b100 H
b11 E
b10 C
b10 G
b110 A
1"
#560
0"
#565
b11 3
b1 <
b100 :
b100 >
b11 ;
b10 9
b10 =
b1110 8
b110 7
1!
#567
b10000 M
b11110000000000001111111111110100 K
b1111 N
#570
0!
#575
b1111 B
b11111111111111111111111111110100 ?
bx F
bx D
bx H
b0 E
b0 C
b0 G
b1111 A
b11 O
b100 U
b11 V
b10 T
b10 W
b110 S
1"
#580
0"
#585
b11 M
1L
04
b11111111111111111111111111110100 5
bx <
bx :
bx >
b0 ;
b0 9
b0 =
b1111 8
b1111 7
1!
#587
b100 M
0L
b10010001000100010000000000000000 K
1I
b11 N
#590
0!
#595
0P
b11111111111111111111111111110100 Q
bx U
b0 V
b0 T
b0 W
b1111 S
1@
b11 B
b0 ?
b10100 F
b10100 D
b10100 H
b1 E
b1 C
b1 G
b1001 A
1"
#600
0"
#605
16
1!
#607
b101 M
0I
b100 N
#610
0!
#615
0@
b100 B
1R
1"
#620
0"
#625
b10100 3
14
b0 5
b10100 <
b10100 :
b10100 >
b1 ;
b1 9
b1 =
b100 8
b1001 7
06
1!
#627
b110 M
b101 N
#630
0!
#635
1P
b10100 O
b0 Q
b10100 U
b1 V
b1 T
b1 W
b1001 S
0R
b101 B
1"
#640
0"
#645
b101 8
1!
#647
b111 M
b110 N
#650
0!
#655
b110 B
1"
#660
0"
#665
b110 8
1!
#667
b1000 M
b11000100001000110000000000000000 K
b111 N
#670
0!
#675
b111 B
b1 F
b11 D
b1 H
b11 E
b10 C
b100 G
b1100 A
1"
#680
0"
#685
b1 3
b1 <
b11 :
b1 >
b11 ;
b10 9
b100 =
b111 8
b1100 7
1!
#687
b1001 M
b10010001000100010000000000000000 K
b1000 N
#690
0!
#695
b1000 B
b10100 F
b10100 D
b10100 H
b1 E
b1 C
b1 G
b1001 A
b1 O
b11 U
b11 V
b10 T
b100 W
b1100 S
1"
#700
0"
#705
b10100 3
b10100 <
b10100 :
b10100 >
b1 ;
b1 9
b1 =
b1000 8
b1001 7
1!
#707
b1010 M
b1001 N
#710
0!
#715
b10100 O
b10100 U
b1 V
b1 T
b1 W
b1001 S
b1001 B
1"
#720
0"
#725
b1001 8
1!
#727
b1011 M
b1010 N
#730
0!
#735
b1010 B
1"
#740
0"
#745
b1010 8
1!
#747
b1100 M
b1011 N
#750
0!
#755
b1011 B
1"
#760
0"
#765
b1011 8
1!
#767
b1101 M
b11010100000000000000000000000100 K
b1100 N
#770
0!
#775
b1100 B
b100 ?
bx F
bx D
b1 H
b0 E
b0 C
b100 G
b1101 A
1"
#780
0"
#785
04
b100 5
bx <
bx :
b1 >
b0 ;
b0 9
b100 =
b1100 8
b1101 7
1!
#787
b1110 M
b1110001000100100000000000000000 K
b1101 N
#790
0!
#795
0P
b100 Q
bx U
b0 V
b0 T
b100 W
b1101 S
b1101 B
b0 ?
b11 F
b10100 D
b10100 H
b10 E
b1 C
b1 G
b111 A
1"
#800
0"
#805
b111100 3
14
b0 5
b11 <
b10100 :
b10100 >
b10 ;
b1 9
b1 =
b1101 8
b111 7
1!
#807
b1111 M
b1100010001000110000000000000000 K
b1110 N
#810
0!
#815
b1110 B
b1 F
b11 D
b11 H
b11 E
b10 C
b10 G
b110 A
1P
b111100 O
b0 Q
b10100 U
b10 V
b1 T
b1 W
b111 S
1"
#820
0"
#825
b10 3
b1 <
b11 :
b11 >
b11 ;
b10 9
b10 =
b1110 8
b110 7
1!
#827
b10000 M
b11110000000000001111111111110100 K
b1111 N
#830
0!
#835
b10 O
b11 U
b11 V
b10 T
b10 W
b110 S
b1111 B
b11111111111111111111111111110100 ?
bx F
bx D
bx H
b0 E
b0 C
b0 G
b1111 A
1"
#840
0"
#845
b11 M
1L
04
b11111111111111111111111111110100 5
bx <
bx :
bx >
b0 ;
b0 9
b0 =
b1111 8
b1111 7
1!
#847
b100 M
0L
b10010001000100010000000000000000 K
1I
b11 N
#850
0!
#855
1@
b11 B
b0 ?
b111100 F
b111100 D
b111100 H
b1 E
b1 C
b1 G
b1001 A
0P
b11111111111111111111111111110100 Q
bx U
b0 V
b0 T
b0 W
b1111 S
1"
#860
0"
#865
16
1!
#867
b101 M
0I
b100 N
#870
0!
#875
1R
0@
b100 B
1"
#880
0"
#885
b111100 3
14
b0 5
b111100 <
b111100 :
b111100 >
b1 ;
b1 9
b1 =
b100 8
b1001 7
06
1!
#887
b110 M
b101 N
#890
0!
#895
b101 B
1P
b111100 O
b0 Q
b111100 U
b1 V
b1 T
b1 W
b1001 S
0R
1"
#900
0"
#905
b101 8
1!
#907
b111 M
b110 N
#910
0!
#915
b110 B
1"
#920
0"
#925
b110 8
1!
#927
b1000 M
b11000100001000110000000000000000 K
b111 N
#930
0!
#935
b111 B
b1 F
b10 D
b1 H
b11 E
b10 C
b100 G
b1100 A
1"
#940
0"
#945
b1 3
b1 <
b10 :
b1 >
b11 ;
b10 9
b100 =
b111 8
b1100 7
1!
#947
b1001 M
b10010001000100010000000000000000 K
b1000 N
#950
0!
#955
b1 O
b10 U
b11 V
b10 T
b100 W
b1100 S
b1000 B
b111100 F
b111100 D
b111100 H
b1 E
b1 C
b1 G
b1001 A
1"
#960
0"
#965
b111100 3
b111100 <
b111100 :
b111100 >
b1 ;
b1 9
b1 =
b1000 8
b1001 7
1!
#967
b1010 M
b1001 N
#970
0!
#975
b1001 B
b111100 O
b111100 U
b1 V
b1 T
b1 W
b1001 S
1"
#980
0"
#985
b1001 8
1!
#987
b1011 M
b1010 N
#990
0!
#995
b1010 B
1"
#1000
0"
#1005
b1010 8
1!
#1007
b1100 M
b1011 N
#1010
0!
#1015
b1011 B
1"
#1020
0"
#1025
b1011 8
1!
#1027
b1101 M
b11010100000000000000000000000100 K
b1100 N
#1030
0!
#1035
b1100 B
b100 ?
bx F
bx D
b1 H
b0 E
b0 C
b100 G
b1101 A
1"
#1040
0"
#1045
04
b100 5
bx <
bx :
b1 >
b0 ;
b0 9
b100 =
b1100 8
b1101 7
1!
#1047
b1110 M
b1110001000100100000000000000000 K
b1101 N
#1050
0!
#1055
b1101 B
b0 ?
b10 F
b111100 D
b111100 H
b10 E
b1 C
b1 G
b111 A
0P
b100 Q
bx U
b0 V
b0 T
b100 W
b1101 S
1"
#1060
0"
#1065
b1111000 3
14
b0 5
b10 <
b111100 :
b111100 >
b10 ;
b1 9
b1 =
b1101 8
b111 7
1!
#1067
b1111 M
b1100010001000110000000000000000 K
b1110 N
#1070
0!
#1075
1P
b1111000 O
b0 Q
b111100 U
b10 V
b1 T
b1 W
b111 S
b1110 B
b1 F
b10 D
b10 H
b11 E
b10 C
b10 G
b110 A
1"
#1080
0"
#1085
b1 3
b1 <
b10 :
b10 >
b11 ;
b10 9
b10 =
b1110 8
b110 7
1!
#1087
b10000 M
b11110000000000001111111111110100 K
b1111 N
#1090
0!
#1095
b1111 B
b11111111111111111111111111110100 ?
bx F
bx D
bx H
b0 E
b0 C
b0 G
b1111 A
b1 O
b10 U
b11 V
b10 T
b10 W
b110 S
1"
#1100
0"
#1105
b11 M
1L
04
b11111111111111111111111111110100 5
bx <
bx :
bx >
b0 ;
b0 9
b0 =
b1111 8
b1111 7
1!
#1107
b100 M
0L
b10010001000100010000000000000000 K
1I
b11 N
#1110
0!
#1115
0P
b11111111111111111111111111110100 Q
bx U
b0 V
b0 T
b0 W
b1111 S
1@
b11 B
b0 ?
b1111000 F
b1111000 D
b1111000 H
b1 E
b1 C
b1 G
b1001 A
1"
#1120
0"
#1125
16
1!
#1127
b101 M
0I
b100 N
#1130
0!
#1135
0@
b100 B
1R
1"
#1140
0"
#1145
b1111000 3
14
b0 5
b1111000 <
b1111000 :
b1111000 >
b1 ;
b1 9
b1 =
b100 8
b1001 7
06
1!
#1147
b110 M
b101 N
#1150
0!
#1155
1P
b1111000 O
b0 Q
b1111000 U
b1 V
b1 T
b1 W
b1001 S
0R
b101 B
1"
#1160
0"
#1165
b101 8
1!
#1167
b111 M
b110 N
#1170
0!
#1175
b110 B
1"
#1180
0"
#1185
b110 8
1!
#1187
b1000 M
b11000100001000110000000000000000 K
b111 N
#1190
0!
#1195
b111 B
b1 F
b1 D
b1 H
b11 E
b10 C
b100 G
b1100 A
1"
