processor/processor.v
module processor(clock1, clock2);
  // 2-phase clocks:
  // - for controlled operations in each pipeline stage
  // With a single clock activating all stages at once, the successive
  // pipeline stages can work incorrectly if the input for one stage doesn't
  // arrive in time from the previous stage.
  // With 2-phase clocks each adjacent stages will be activated alternately
  // avoid this scenerio
  input clock1, clock2;

  reg [31:0] register_bank [0:15];
  reg [31:0] instruction_memory [0:1023];
  reg [31:0] data_memory [0:1023];

  // opcodes
  parameter 
    HLT = 4'b0000,
    MOV = 4'b0001,
    MVI = 4'b0010,
    LOD = 4'b0011,
    STR = 4'b0100,
    ADD = 4'b0101,
    SUB = 4'b0110,
    MUL = 4'b0111,
    AND = 4'b1000,
    ORR = 4'b1001,
    NOT = 4'b1010,
    LES = 4'b1011,
    GTR = 4'b1100,
    JEZ = 4'b1101,
    JNZ = 4'b1110,
    JMP = 4'b1111;

    

  // ----- instruction fetch (if) stage -----
  
  // states
  reg [31:0] if_pc, if_next_pc, if_ir;
  reg if_halted, if_branch_taken, if_next_branch_taken;

  initial
  begin
    if_halted <= 0;
    if_next_pc <= 0;
    if_next_branch_taken <= 0;
    id_invalid <= 1;
    ex_invalid <= 1;
    ma_invalid <= 1;
  end
  
  always @ (posedge clock1) 
  begin
    // if and ex stages are activated by the same clock 
    // so waiting some time to let the branch and halted signals from ex
    // stage come in
    #2;
    if (if_halted == 0)
    begin
      if_pc = if_next_pc;
      if_branch_taken = if_next_branch_taken;
      if (if_branch_taken == 1)
      begin
        if_ir = instruction_memory[if_pc];
        if_next_branch_taken = 0;
        if_next_pc = if_pc + 1;
      end
      else 
      begin
        if_ir = instruction_memory[if_pc];
        if_next_pc = if_pc + 1;
      end
    end
  end



  // ----- instruction decode (id) stage -----

  // states
  reg [3:0] id_opcode, id_rdest, id_ra, id_rb;
  reg [31:0] id_pc, id_rdest_val, id_ra_val, id_rb_val, id_immediate;
  reg id_invalid; // due to branch jump or program being halted, the instruction in this stage of pipeline can be invalid

  always @ (posedge clock2)
  begin 
    // instruction decoding
    id_opcode <= if_ir[31:28];
    id_rdest <= if_ir[27:24];
    id_ra <= if_ir[23:20];
    id_rb <= if_ir[19:16];
    id_rdest_val <= register_bank[if_ir[27:24]]; // register prefetching
    id_ra_val <= register_bank[if_ir[23:20]];
    id_rb_val <= register_bank[if_ir[19:16]];
    // 16-bit signed immediate number need to be converted to 32-bits
    // for that the signed bit needs to be copied as 16-MSBs
    id_immediate <= {{16{if_ir[15]}}, {if_ir[15:0]}};

    id_pc <= if_pc;
    id_invalid <= (if_branch_taken | if_halted) ? 1: 0;
  end




  // ----- execute (ex) stage: ALU and branch instruction execution -----

  // states
  reg [3:0] ex_opcode, ex_rdest, ex_ra, ex_rb;
  reg [31:0] ex_alu_result, ex_pc, ex_rdest_val, ex_ra_val, ex_rb_val, ex_immediate;
  reg ex_invalid, ex_has_result;


  always @ (posedge clock1) 
  begin
    if (id_invalid == 0) 
    begin
      ex_invalid <= 0;
      ex_opcode <= id_opcode;
      ex_pc <= id_pc;
      ex_rdest <= id_rdest;
      ex_ra <= id_ra;
      ex_rb <= id_rb;
      ex_rdest_val <= id_rdest_val;
      ex_ra_val <= id_ra_val;
      ex_rb_val <= id_rb_val;
      ex_immediate <= id_immediate;
      case (id_opcode)
        ADD: begin ex_has_result <= 1; ex_alu_result <= id_ra_val + id_rb_val; end
        SUB: begin ex_has_result <= 1; ex_alu_result <= id_ra_val - id_rb_val; end
        MUL: begin ex_has_result <= 1; ex_alu_result <= id_ra_val * id_rb_val; end
        AND: begin ex_has_result <= 1; ex_alu_result <= id_ra_val & id_rb_val; end
        ORR: begin ex_has_result <= 1; ex_alu_result <= id_ra_val | id_rb_val; end
        NOT: begin ex_has_result <= 1; ex_alu_result <= ~id_ra_val; end
        LES: begin ex_has_result <= 1; ex_alu_result <= (id_ra_val < id_rb_val) ? 1 : 0; end
        GTR: begin ex_has_result <= 1; ex_alu_result <= (id_ra_val > id_rb_val) ? 1 : 0; end
        JEZ: begin
          ex_has_result <= 0;
          if (id_rdest_val == 0) begin
            if_next_branch_taken <= 1;
            if_next_pc <= id_pc + id_immediate; // pc = pc + offset
          end
        end
        JNZ: begin
          ex_has_result <= 0;
          if (id_rdest_val != 0) begin
            if_next_branch_taken <= 1;
            if_next_pc <= id_pc + id_immediate; // pc = pc + offset
          end
        end
        JMP: begin
          ex_has_result <= 0;
          begin
            if_next_branch_taken <= 1;
            if_next_pc <= id_pc + id_immediate; // pc = pc + offset
          end
        end
        HLT: begin ex_has_result <= 0; if_halted <= 1; end
      endcase
    end
    else ex_invalid <= 1;
  end



  // ----- memory access (ma) stage: memory store and load instruction execution -----

  // states
  reg [3:0] ma_opcode, ma_rdest, ma_ra, ma_rb;
  reg [31:0] ma_alu_result, ma_ra_val, ma_immediate;
  reg ma_invalid, ma_has_result;
  
  always @ (posedge clock2)
  begin
    if (ex_invalid == 0)
    begin
      ma_invalid <= 0;
      ma_opcode <= ex_opcode;
      ma_rdest <= ex_rdest;
      ma_ra <= ex_ra;
      ma_rb <= ex_rb;
      ma_ra_val <= ex_ra_val;
      ma_immediate <= ex_immediate;
      ma_alu_result <= ex_alu_result;
      ma_has_result <= ex_has_result;
      case (ex_opcode)
        LOD: register_bank[ex_rdest] <= data_memory[ex_ra_val + ex_immediate];
        STR: data_memory[ex_ra_val + ex_immediate] <= register_bank[ex_rdest];
      endcase
    end
    else ma_invalid <= 1;
  end



  // ----- write-back (wb) stage: register move instr. + ALU result writeback

  always @ (posedge clock1)
  begin
    if (ma_invalid == 0)
    begin
      if (ma_has_result == 1) begin 
        register_bank[ma_rdest] <= ma_alu_result;
      end
      case (ma_opcode)
        MOV: register_bank[ma_rdest] <= ma_ra_val;
        MVI: register_bank[ma_rdest] <= ma_immediate;
      endcase
    end
  end


endmodule

processor/tests/gcd/test_gcd.v
/*
Assembling gcd.s ---

---------------------------  debug info  ---------------------------
   #0             MVI R1, 78          0010 0001 0000 0000 0000000001001110
   #1             MVI R2, 143         0010 0010 0000 0000 0000000010001111
   #2      :loop  ORR R5, R5, R5      1001 0101 0101 0101 0000000000000000
   #3             ORR R5, R5, R5      1001 0101 0101 0101 0000000000000000
   #4             ORR R5, R5, R5      1001 0101 0101 0101 0000000000000000
   #5             ORR R5, R5, R5      1001 0101 0101 0101 0000000000000000
   #6             ORR R5, R5, R5      1001 0101 0101 0101 0000000000000000
   #7             SUB R3, R1, R2      0110 0011 0001 0010 0000000000000000
   #8             ORR R5, R5, R5      1001 0101 0101 0101 0000000000000000
   #9             ORR R5, R5, R5      1001 0101 0101 0101 0000000000000000
  #10             ORR R5, R5, R5      1001 0101 0101 0101 0000000000000000
  #11             ORR R5, R5, R5      1001 0101 0101 0101 0000000000000000
  #12             ORR R5, R5, R5      1001 0101 0101 0101 0000000000000000
  #13             JEZ R3, end         1101 0011 0000 0000 0000000000001100
  #14             GTR R3, R1, R2      1100 0011 0001 0010 0000000000000000
  #15             ORR R5, R5, R5      1001 0101 0101 0101 0000000000000000
  #16             ORR R5, R5, R5      1001 0101 0101 0101 0000000000000000
  #17             ORR R5, R5, R5      1001 0101 0101 0101 0000000000000000
  #18             ORR R5, R5, R5      1001 0101 0101 0101 0000000000000000
  #19             ORR R5, R5, R5      1001 0101 0101 0101 0000000000000000
  #20             JNZ R3, greater     1110 0011 0000 0000 0000000000000011
  #21             SUB R2, R2, R1      0110 0010 0010 0001 0000000000000000
  #22             JMP loop            1111 0000 0000 0000 1111111111101100
  #23   :greater  SUB R1, R1, R2      0110 0001 0001 0010 0000000000000000
  #24             JMP loop            1111 0000 0000 0000 1111111111101010
  #25       :end  HLT                 0000 0000 0000 0000 0000000000000000

----- assembled instructions -------
553648206
570425487
2505375744
2505375744
2505375744
2505375744
2505375744
1662124032
2505375744
2505375744
2505375744
2505375744
2505375744
3539992588
3272736768
2505375744
2505375744
2505375744
2505375744
2505375744
3808428035
1646329856
4026597356
1628569600
4026597354
0

----- generated code -------
computer.instruction_memory[0]=553648206;
computer.instruction_memory[1]=570425487;
computer.instruction_memory[2]=2505375744;
computer.instruction_memory[3]=2505375744;
computer.instruction_memory[4]=2505375744;
computer.instruction_memory[5]=2505375744;
computer.instruction_memory[6]=2505375744;
computer.instruction_memory[7]=1662124032;
computer.instruction_memory[8]=2505375744;
computer.instruction_memory[9]=2505375744;
computer.instruction_memory[10]=2505375744;
computer.instruction_memory[11]=2505375744;
computer.instruction_memory[12]=2505375744;
computer.instruction_memory[13]=3539992588;
computer.instruction_memory[14]=3272736768;
computer.instruction_memory[15]=2505375744;
computer.instruction_memory[16]=2505375744;
computer.instruction_memory[17]=2505375744;
computer.instruction_memory[18]=2505375744;
computer.instruction_memory[19]=2505375744;
computer.instruction_memory[20]=3808428035;
computer.instruction_memory[21]=1646329856;
computer.instruction_memory[22]=4026597356;
computer.instruction_memory[23]=1628569600;
computer.instruction_memory[24]=4026597354;
computer.instruction_memory[25]=0;

*/

module test_gcd;
reg clock1, clock2;

processor computer(clock1, clock2);

// generate 2-phase clock
initial
begin
  clock1 = 0; clock2 = 0;
  forever begin
      #5 clock1 = 1;
      #5 clock1 = 0;
      #5 clock2 = 1;
      #5 clock2 = 0;
  end
end

initial 
begin
  computer.instruction_memory[0]=553648206;
  computer.instruction_memory[1]=570425487;
  computer.instruction_memory[2]=2505375744;
  computer.instruction_memory[3]=2505375744;
  computer.instruction_memory[4]=2505375744;
  computer.instruction_memory[5]=2505375744;
  computer.instruction_memory[6]=2505375744;
  computer.instruction_memory[7]=1662124032;
  computer.instruction_memory[8]=2505375744;
  computer.instruction_memory[9]=2505375744;
  computer.instruction_memory[10]=2505375744;
  computer.instruction_memory[11]=2505375744;
  computer.instruction_memory[12]=2505375744;
  computer.instruction_memory[13]=3539992588;
  computer.instruction_memory[14]=3272736768;
  computer.instruction_memory[15]=2505375744;
  computer.instruction_memory[16]=2505375744;
  computer.instruction_memory[17]=2505375744;
  computer.instruction_memory[18]=2505375744;
  computer.instruction_memory[19]=2505375744;
  computer.instruction_memory[20]=3808428035;
  computer.instruction_memory[21]=1646329856;
  computer.instruction_memory[22]=4026597356;
  computer.instruction_memory[23]=1628569600;
  computer.instruction_memory[24]=4026597354;
  computer.instruction_memory[25]=0;
end

initial
begin
  $dumpfile("test_gcd.vcd");
  $dumpvars(0, test_gcd);
end

initial
begin
  $monitor("completed: %1b     X: %3d, Y: %3d     GCD(X,Y): %3d", computer.if_halted, computer.register_bank[1], computer.register_bank[2], computer.register_bank[1]);
  #5000 $finish;
end

endmodule

processor/tests/gcd/test_gcd.vcd
$date
	Mon May 27 00:05:06 2024
$end
$version
	Icarus Verilog
$end
$timescale
	1s
$end
$scope module test_gcd $end
$var reg 1 ! clock1 $end
$var reg 1 " clock2 $end
$scope module computer $end
$var wire 1 ! clock1 $end
$var wire 1 " clock2 $end
$var parameter 4 # ADD $end
$var parameter 4 $ AND $end
$var parameter 4 % GTR $end
$var parameter 4 & HLT $end
$var parameter 4 ' JEZ $end
$var parameter 4 ( JMP $end
$var parameter 4 ) JNZ $end
$var parameter 4 * LES $end
$var parameter 4 + LOD $end
$var parameter 4 , MOV $end
$var parameter 4 - MUL $end
$var parameter 4 . MVI $end
$var parameter 4 / NOT $end
$var parameter 4 0 ORR $end
$var parameter 4 1 STR $end
$var parameter 4 2 SUB $end
$var reg 32 3 ex_alu_result [31:0] $end
$var reg 1 4 ex_has_result $end
$var reg 32 5 ex_immediate [31:0] $end
$var reg 1 6 ex_invalid $end
$var reg 4 7 ex_opcode [3:0] $end
$var reg 32 8 ex_pc [31:0] $end
$var reg 4 9 ex_ra [3:0] $end
$var reg 32 : ex_ra_val [31:0] $end
$var reg 4 ; ex_rb [3:0] $end
$var reg 32 < ex_rb_val [31:0] $end
$var reg 4 = ex_rdest [3:0] $end
$var reg 32 > ex_rdest_val [31:0] $end
$var reg 32 ? id_immediate [31:0] $end
$var reg 1 @ id_invalid $end
$var reg 4 A id_opcode [3:0] $end
$var reg 32 B id_pc [31:0] $end
$var reg 4 C id_ra [3:0] $end
$var reg 32 D id_ra_val [31:0] $end
$var reg 4 E id_rb [3:0] $end
$var reg 32 F id_rb_val [31:0] $end
$var reg 4 G id_rdest [3:0] $end
$var reg 32 H id_rdest_val [31:0] $end
$var reg 1 I if_branch_taken $end
$var reg 1 J if_halted $end
$var reg 32 K if_ir [31:0] $end
$var reg 1 L if_next_branch_taken $end
$var reg 32 M if_next_pc [31:0] $end
$var reg 32 N if_pc [31:0] $end
$var reg 32 O ma_alu_result [31:0] $end
$var reg 1 P ma_has_result $end
$var reg 32 Q ma_immediate [31:0] $end
$var reg 1 R ma_invalid $end
$var reg 4 S ma_opcode [3:0] $end
$var reg 4 T ma_ra [3:0] $end
$var reg 32 U ma_ra_val [31:0] $end
$var reg 4 V ma_rb [3:0] $end
$var reg 4 W ma_rdest [3:0] $end
$upscope $end
$upscope $end
$enddefinitions $end
$comment Show the parameter values. $end
$dumpall
b110 2
b100 1
b1001 0
b1010 /
b10 .
b111 -
b1 ,
b11 +
b1011 *
b1110 )
b1111 (
b1101 '
b0 &
b1100 %
b1000 $
b101 #
$end
#0
$dumpvars
bx W
bx V
bx U
bx T
bx S
1R
bx Q
xP
bx O
bx N
b0 M
0L
bx K
0J
xI
bx H
bx G
bx F
bx E
bx D
bx C
bx B
bx A
1@
bx ?
bx >
bx =
bx <
bx ;
bx :
bx 9
bx 8
bx 7
16
bx 5
x4
bx 3
0"
0!
$end
#5
1!
#7
b1 M
b100001000000000000000001001110 K
0I
b0 N
#10
0!
#15
0@
b0 B
b1001110 ?
b0 E
b0 C
b1 G
b10 A
1"
#20
0"
#25
b1001110 5
b0 ;
b0 9
b1 =
b0 8
b10 7
06
1!
#27
b10 M
b100010000000000000000010001111 K
b1 N
#30
0!
#35
b1001110 Q
b0 V
b0 T
b1 W
b10 S
0R
b1 B
b10001111 ?
b10 G
1"
#40
0"
#45
b10001111 5
b10 =
b1 8
1!
#47
b11 M
b10010101010101010000000000000000 K
b10 N
#50
0!
#55
b10 B
b0 ?
b101 E
b101 C
b101 G
b1001 A
b10001111 Q
b10 W
1"
#60
0"
#65
14
b0 5
b101 ;
b101 9
b101 =
b10 8
b1001 7
1!
#67
b100 M
b11 N
#70
0!
#75
1P
b0 Q
b101 V
b101 T
b101 W
b1001 S
b11 B
1"
#80
0"
#85
b11 8
1!
#87
b101 M
b100 N
#90
0!
#95
b100 B
1"
#100
0"
#105
b100 8
1!
#107
b110 M
b101 N
#110
0!
#115
b101 B
1"
#120
0"
#125
b101 8
1!
#127
b111 M
b110 N
#130
0!
#135
b110 B
1"
#140
0"
#145
b110 8
1!
#147
b1000 M
b1100011000100100000000000000000 K
b111 N
#150
0!
#155
b111 B
b10001111 F
b1001110 D
b10 E
b1 C
b11 G
b110 A
1"
#160
0"
#165
b11111111111111111111111110111111 3
b10001111 <
b1001110 :
b10 ;
b1 9
b11 =
b111 8
b110 7
1!
#167
b1001 M
b10010101010101010000000000000000 K
b1000 N
#170
0!
#175
b1000 B
bx F
bx D
b101 E
b101 C
b101 G
b1001 A
b11111111111111111111111110111111 O
b1001110 U
b10 V
b1 T
b11 W
b110 S
1"
#180
0"
#185
bx 3
bx <
bx :
b101 ;
b101 9
b101 =
b1000 8
b1001 7
1!
#187
b1010 M
b1001 N
#190
0!
#195
bx O
bx U
b101 V
b101 T
b101 W
b1001 S
b1001 B
1"
#200
0"
#205
b1001 8
1!
#207
b1011 M
b1010 N
#210
0!
#215
b1010 B
1"
#220
0"
#225
b1010 8
1!
#227
b1100 M
b1011 N
#230
0!
#235
b1011 B
1"
#240
0"
#245
b1011 8
1!
#247
b1101 M
b1100 N
#250
0!
#255
b1100 B
1"
#260
0"
#265
b1100 8
1!
#267
b1110 M
b11010011000000000000000000001100 K
b1101 N
#270
0!
#275
b1101 B
b1100 ?
b11111111111111111111111110111111 H
b0 E
b0 C
b11 G
b1101 A
1"
#280
0"
#285
04
b1100 5
b11111111111111111111111110111111 >
b0 ;
b0 9
b11 =
b1101 8
b1101 7
1!
#287
b1111 M
b11000011000100100000000000000000 K
b1110 N
#290
0!
#295
b1110 B
b0 ?
b10001111 F
b1001110 D
b10 E
b1 C
b1100 A
0P
b1100 Q
b0 V
b0 T
b11 W
b1101 S
1"
#300
0"
#305
b0 3
14
b0 5
b10001111 <
b1001110 :
b10 ;
b1 9
b1110 8
b1100 7
1!
#307
b10000 M
b10010101010101010000000000000000 K
b1111 N
#310
0!
#315
1P
b0 O
b0 Q
b1001110 U
b10 V
b1 T
b1100 S
b1111 B
bx F
bx D
bx H
b101 E
b101 C
b101 G
b1001 A
1"
#320
0"
#325
bx 3
bx <
bx :
bx >
b101 ;
b101 9
b101 =
b1111 8
b1001 7
1!
#327
b10001 M
b10000 N
#330
0!
#335
b10000 B
bx O
bx U
b101 V
b101 T
b101 W
b1001 S
1"
#340
0"
#345
b10000 8
1!
#347
b10010 M
b10001 N
#350
0!
#355
b10001 B
1"
#360
0"
#365
b10001 8
1!
#367
b10011 M
b10010 N
#370
0!
#375
b10010 B
1"
#380
0"
#385
b10010 8
1!
#387
b10100 M
b10011 N
#390
0!
#395
b10011 B
1"
#400
0"
#405
b10011 8
1!
#407
b10101 M
b11100011000000000000000000000011 K
b10100 N
#410
0!
#415
b10100 B
b11 ?
b0 H
b0 E
b0 C
b11 G
b1110 A
1"
#420
0"
#425
04
b11 5
b0 >
b0 ;
b0 9
b11 =
b10100 8
b1110 7
1!
#427
b10110 M
b1100010001000010000000000000000 K
b10101 N
#430
0!
#435
0P
b11 Q
b0 V
b0 T
b11 W
b1110 S
b10101 B
b0 ?
b1001110 F
b10001111 D
b10001111 H
b1 E
b10 C
b10 G
b110 A
1"
#440
0"
#445
b1000001 3
14
b0 5
b1001110 <
b10001111 :
b10001111 >
b1 ;
b10 9
b10 =
b10101 8
b110 7
1!
#447
b10111 M
b11110000000000001111111111101100 K
b10110 N
#450
0!
#455
b10110 B
b11111111111111111111111111101100 ?
bx F
bx D
bx H
b0 E
b0 C
b0 G
b1111 A
1P
b1000001 O
b0 Q
b10001111 U
b1 V
b10 T
b10 W
b110 S
1"
#460
0"
#465
b10 M
1L
04
b11111111111111111111111111101100 5
bx <
bx :
bx >
b0 ;
b0 9
b0 =
b10110 8
b1111 7
1!
#467
0L
1I
b10 N
#470
0!
#475
0P
b11111111111111111111111111101100 Q
bx U
b0 V
b0 T
b0 W
b1111 S
1@
b10 B
1"
#480
0"
#485
16
1!
#487
b11 M
b10010101010101010000000000000000 K
0I
#490
0!
#495
0@
b0 ?
b101 E
b101 C
b101 G
b1001 A
1R
1"
#500
0"
#505
bx 3
14
b0 5
b101 ;
b101 9
b101 =
b10 8
b1001 7
06
1!
#507
b100 M
b11 N
#510
0!
#515
1P
bx O
b0 Q
b101 V
b101 T
b101 W
b1001 S
0R
b11 B
1"
#520
0"
#525
b11 8
1!
#527
b101 M
b100 N
#530
0!
#535
b100 B
1"
#540
0"
#545
b100 8
1!
#547
b110 M
b101 N
#550
0!
#555
b101 B
1"
#560
0"
#565
b101 8
1!
#567
b111 M
b110 N
#570
0!
#575
b110 B
1"
#580
0"
#585
b110 8
1!
#587
b1000 M
b1100011000100100000000000000000 K
b111 N
#590
0!
#595
b111 B
b1000001 F
b1001110 D
b0 H
b10 E
b1 C
b11 G
b110 A
1"
#600
0"
#605
b1101 3
b1000001 <
b1001110 :
b0 >
b10 ;
b1 9
b11 =
b111 8
b110 7
1!
#607
b1001 M
b10010101010101010000000000000000 K
b1000 N
#610
0!
#615
b1000 B
bx F
bx D
bx H
b101 E
b101 C
b101 G
b1001 A
b1101 O
b1001110 U
b10 V
b1 T
b11 W
b110 S
1"
#620
0"
#625
bx 3
bx <
bx :
bx >
b101 ;
b101 9
b101 =
b1000 8
b1001 7
1!
#627
b1010 M
b1001 N
#630
0!
#635
bx O
bx U
b101 V
b101 T
b101 W
b1001 S
b1001 B
1"
#640
0"
#645
b1001 8
1!
#647
b1011 M
b1010 N
#650
0!
#655
b1010 B
1"
#660
0"
#665
b1010 8
1!
#667
b1100 M
b1011 N
#670
0!
#675
b1011 B
1"
#680
0"
#685
b1011 8
1!
#687
b1101 M
b1100 N
#690
0!
#695
b1100 B
1"
#700
0"
#705
b1100 8
1!
#707
b1110 M
b11010011000000000000000000001100 K
b1101 N
#710
0!
#715
b1101 B
b1100 ?
b1101 H
b0 E
b0 C
b11 G
b1101 A
1"
#720
0"
#725
04
b1100 5
b1101 >
b0 ;
b0 9
b11 =
b1101 8
b1101 7
1!
#727
b1111 M
b11000011000100100000000000000000 K
b1110 N
#730
0!
#735
b1110 B
b0 ?
b1000001 F
b1001110 D
b10 E
b1 C
b1100 A
0P
b1100 Q
b0 V
b0 T
b11 W
b1101 S
1"
#740
0"
#745
b1 3
14
b0 5
b1000001 <
b1001110 :
b10 ;
b1 9
b1110 8
b1100 7
1!
#747
b10000 M
b10010101010101010000000000000000 K
b1111 N
#750
0!
#755
1P
b1 O
b0 Q
b1001110 U
b10 V
b1 T
b1100 S
b1111 B
bx F
bx D
bx H
b101 E
b101 C
b101 G
b1001 A
1"
#760
0"
#765
bx 3
bx <
bx :
bx >
b101 ;
b101 9
b101 =
b1111 8
b1001 7
1!
#767
b10001 M
b10000 N
#770
0!
#775
b10000 B
bx O
bx U
b101 V
b101 T
b101 W
b1001 S
1"
#780
0"
#785
b10000 8
1!
#787
b10010 M
b10001 N
#790
0!
#795
b10001 B
1"
#800
0"
#805
b10001 8
1!
#807
b10011 M
b10010 N
#810
0!
#815
b10010 B
1"
#820
0"
#825
b10010 8
1!
#827
b10100 M
b10011 N
#830
0!
#835
b10011 B
1"
#840
0"
#845
b10011 8
1!
#847
b10101 M
b11100011000000000000000000000011 K
b10100 N
#850
0!
#855
b10100 B
b11 ?
b1 H
b0 E
b0 C
b11 G
b1110 A
1"
#860
0"
#865
b10111 M
1L
04
b11 5
b1 >
b0 ;
b0 9
b11 =
b10100 8
b1110 7
1!
#867
0L
1I
b10111 N
#870
0!
#875
0P
b11 Q
b0 V
b0 T
b11 W
b1110 S
1@
b10111 B
1"
#880
0"
#885
16
1!
#887
b11000 M
b1100001000100100000000000000000 K
0I
#890
0!
#895
0@
b0 ?
b1000001 F
b1001110 D
b1001110 H
b10 E
b1 C
b1 G
b110 A
1R
1"
#900
0"
#905
b1101 3
14
b0 5
b1000001 <
b1001110 :
b1001110 >
b10 ;
b1 9
b1 =
b10111 8
b110 7
06
1!
#907
b11001 M
b11110000000000001111111111101010 K
b11000 N
#910
0!
#915
1P
b1101 O
b0 Q
b1001110 U
b10 V
b1 T
b1 W
b110 S
0R
b11000 B
b11111111111111111111111111101010 ?
bx F
bx D
bx H
b0 E
b0 C
b0 G
b1111 A
1"
#920
0"
#925
b10 M
1L
04
b11111111111111111111111111101010 5
bx <
bx :
bx >
b0 ;
b0 9
b0 =
b11000 8
b1111 7
1!
#927
0L
1I
b10 N
#930
0!
#935
1@
b10 B
0P
b11111111111111111111111111101010 Q
bx U
b0 V
b0 T
b0 W
b1111 S
1"
#940
0"
#945
16
1!
#947
b11 M
b10010101010101010000000000000000 K
0I
#950
0!
#955
1R
0@
b0 ?
b101 E
b101 C
b101 G
b1001 A
1"
#960
0"
#965
bx 3
14
b0 5
b101 ;
b101 9
b101 =
b10 8
b1001 7
06
1!
#967
b100 M
b11 N
#970
0!
#975
b11 B
1P
bx O
b0 Q
b101 V
b101 T
b101 W
b1001 S
0R
1"
#980
0"
#985
b11 8
1!
#987
b101 M
b100 N
#990
0!
#995
b100 B
1"
#1000
0"
#1005
b100 8
1!
#1007
b110 M
b101 N
#1010
0!
#1015
b101 B
1"
#1020
0"
#1025
b101 8
1!
#1027
b111 M
b110 N
#1030
0!
#1035
b110 B
1"
#1040
0"
#1045
b110 8
1!
#1047
b1000 M
b1100011000100100000000000000000 K
b111 N
#1050
0!
#1055
b111 B
b1000001 F
b1101 D
b1 H
b10 E
b1 C
b11 G
b110 A
1"
#1060
0"
#1065
b11111111111111111111111111001100 3
b1000001 <
b1101 :
b1 >
b10 ;
b1 9
b11 =
b111 8
b110 7
1!
#1067
b1001 M
b10010101010101010000000000000000 K
b1000 N
#1070
0!
#1075
b11111111111111111111111111001100 O
b1101 U
b10 V
b1 T
b11 W
b110 S
b1000 B
bx F
bx D
bx H
b101 E
b101 C
b101 G
b1001 A
1"
#1080
0"
#1085
bx 3
bx <
bx :
bx >
b101 ;
b101 9
b101 =
b1000 8
b1001 7
1!
#1087
b1010 M
b1001 N
#1090
0!
#1095
b1001 B
bx O
bx U
b101 V
b101 T
b101 W
b1001 S
1"
#1100
0"
#1105
b1001 8
1!
#1107
b1011 M
b1010 N
#1110
0!
#1115
b1010 B
1"
#1120
0"
#1125
b1010 8
1!
#1127
b1100 M
b1011 N
#1130
0!
#1135
b1011 B
1"
#1140
0"
#1145
b1011 8
1!
#1147
b1101 M
b1100 N
#1150
0!
#1155
b1100 B
1"
#1160
0"
#1165
b1100 8
1!
#1167
b1110 M
b11010011000000000000000000001100 K
b1101 N
#1170
0!
#1175
b1101 B
b1100 ?
b11111111111111111111111111001100 H
b0 E
b0 C
b11 G
b1101 A
1"
#1180
0"
#1185
04
b1100 5
b11111111111111111111111111001100 >
b0 ;
b0 9
b11 =
b1101 8
b1101 7
1!
#1187
b1111 M
b11000011000100100000000000000000 K
b1110 N
#1190
0!
#1195
0P
b1100 Q
b0 V
b0 T
b11 W
b1101 S
b1110 B
b0 ?
b1000001 F
b1101 D
b10 E
b1 C
b1100 A
1"
#1200
0"
#1205
b0 3
14
b0 5
b1000001 <
b1101 :
b10 ;
b1 9
b1110 8
b1100 7
1!
#1207
b10000 M
b10010101010101010000000000000000 K
b1111 N
#1210
0!
#1215
b1111 B
bx F
bx D
bx H
b101 E
b101 C
b101 G
b1001 A
1P
b0 O
b0 Q
b1101 U
b10 V
b1 T
b1100 S
1"
#1220
0"
#1225
bx 3
bx <
bx :
bx >
b101 ;
b101 9
b101 =
b1111 8
b1001 7
1!
#1227
b10001 M
b10000 N
#1230
0!
#1235
bx O
bx U
b101 V
b101 T
b101 W
b1001 S
b10000 B
1"
#1240
0"
#1245
b10000 8
1!
#1247
b10010 M
b10001 N
#1250
0!
#1255
b10001 B
1"
#1260
0"
#1265
b10001 8
1!
#1267
b10011 M
b10010 N
#1270
0!
#1275
b10010 B
1"
#1280
0"
#1285
b10010 8
1!
#1287
b10100 M
b10011 N
#1290
0!
#1295
b10011 B
1"
#1300
0"
#1305
b10011 8
1!
#1307
b10101 M
b11100011000000000000000000000011 K
b10100 N
#1310
0!
#1315
b10100 B
b11 ?
b0 H
b0 E
b0 C
b11 G
b1110 A
1"
#1320
0"
#1325
04
b11 5
b0 >
b0 ;
b0 9
b11 =
b10100 8
b1110 7
1!
#1327
b10110 M
b1100010001000010000000000000000 K
b10101 N
#1330
0!
#1335
b10101 B
b0 ?
b1101 F
b1000001 D
b1000001 H
b1 E
b10 C
b10 G
b110 A
0P
b11 Q
b0 V
b0 T
b11 W
b1110 S
1"
#1340
0"
#1345
b110100 3
14
b0 5
b1101 <
b1000001 :
b1000001 >
b1 ;
b10 9
b10 =
b10101 8
b110 7
1!
#1347
b10111 M
b11110000000000001111111111101100 K
b10110 N
#1350
0!
#1355
1P
b110100 O
b0 Q
b1000001 U
b1 V
b10 T
b10 W
b110 S
b10110 B
b11111111111111111111111111101100 ?
bx F
bx D
bx H
b0 E
b0 C
b0 G
b1111 A
1"
#1360
0"
#1365
b10 M
1L
04
b11111111111111111111111111101100 5
bx <
bx :
bx >
b0 ;
b0 9
b0 =
b10110 8
b1111 7
1!
#1367
0L
1I
b10 N
#1370
0!
#1375
1@
b10 B
0P
b11111111111111111111111111101100 Q
bx U
b0 V
b0 T
b0 W
b1111 S
1"
#1380
0"
#1385
16
1!
#1387
b11 M
b10010101010101010000000000000000 K
0I
#1390
0!
#1395
1R
0@
b0 ?
b101 E
b101 C
b101 G
b1001 A
1"
#1400
0"
#1405
bx 3
14
b0 5
b101 ;
b101 9
b101 =
b10 8
b1001 7
06
1!
#1407
b100 M
b11 N
#1410
0!
#1415
b11 B
1P
bx O
b0 Q
b101 V
b101 T
b101 W
b1001 S
0R
1"
#1420
0"
#1425
b11 8
1!
#1427
b101 M
b100 N
#1430
0!
#1435
b100 B
1"
#1440
0"
#1445
b100 8
1!
#1447
b110 M
b101 N
#1450
0!
#1455
b101 B
1"
#1460
0"
#1465
b101 8
1!
#1467
b111 M
b110 N
#1470
0!
#1475
b110 B
1"
#1480
0"
#1485
b110 8
1!
#1487
b1000 M
b1100011000100100000000000000000 K
b111 N
#1490
0!
#1495
b111 B
b110100 F
b1101 D
b0 H
b10 E
b1 C
b11 G
b110 A
1"
#1500
0"
#1505
b11111111111111111111111111011001 3
b110100 <
b1101 :
b0 >
b10 ;
b1 9
b11 =
b111 8
b110 7
1!
#1507
b1001 M
b10010101010101010000000000000000 K
b1000 N
#1510
0!
#1515
b11111111111111111111111111011001 O
b1101 U
b10 V
b1 T
b11 W
b110 S
b1000 B
bx F
bx D
bx H
b101 E
b101 C
b101 G
b1001 A
1"
#1520
0"
#1525
bx 3
bx <
bx :
bx >
b101 ;
b101 9
b101 =
b1000 8
b1001 7
1!
#1527
b1010 M
b1001 N
#1530
0!
#1535
b1001 B
bx O
bx U
b101 V
b101 T
b101 W
b1001 S
1"
#1540
0"
#1545
b1001 8
1!
#1547
b1011 M
b1010 N
#1550
0!
#1555
b1010 B
1"
#1560
0"
#1565
b1010 8
1!
#1567
b1100 M
b1011 N
#1570
0!
#1575
b1011 B
1"
#1580
0"
#1585
b1011 8
1!
#1587
b1101 M
b1100 N
#1590
0!
#1595
b1100 B
1"
#1600
0"
#1605
b1100 8
1!
